Workbook

Sheet Cover
A1: PRAXION HROS — Team Mobilization & Expense Budget
A3: Document | B3: Praxion HROS — Team Mobilization, Salaries & Expenses
A4: Version | B4: v1.0
A5: Prepared | B5: 2026-04-19
A6: Owner | B6: Mohamed Sabry — CEO / Product Owner
A7: Currency | B7: EGP (Egyptian Pounds)
A8: Horizon | B8: Q2 2026 (May) → Q2 2028 (9 quarters)
A10: Workbook Contents
A11: Assumptions | B11: Global inputs — benefits loading, quarter→month map
A12: Team Roster | B12: All team members with status, start month, rate
A13: Salary Schedule | B13: Quarterly salary cost per person (formula-driven)
A14: Contractors | B14: Vendor / freelance engagements by quarter
A15: Software & Infra | B15: Recurring software, cloud & tooling spend
A16: Hardware & Setup | B16: One-off equipment & setup purchases
A17: Quarterly Summary | B17: Roll-up of all 4 categories by quarter + totals
A19: Colour Legend
A20: Blue text | B20: Hardcoded input — change to run scenarios
A21: Black text | B21: Formula / calculated value
A22: Green text | B22: Cross-sheet reference
A23: Yellow fill | B23: Placeholder — needs user input
A25: Notes
A26: • All figures are in EGP unless explicitly stated otherwise.
A27: • Salaries are shown FULLY LOADED (base + benefits loading from Assumptions).
A28: • Start months align to Assumptions!Month_Map — month 1 = May 2026.
A29: • 'TBH' rows are placeholder hires; adjust start month and rate when finalised.
A30: • Update only the blue input cells — formulas propagate automatically.

Sheet Assumptions
A1: Assumptions & Inputs
A3: Key | B3: Value | C3: Notes
A4: Benefits loading (% of base) | B4: 0.2 | C4: Social insurance, medical, EOS accrual — adjust to company policy
A5: Annual raise assumption | B5: 0.1 | C5: Not yet applied in schedule — reserved for future version
A6: Month 1 anchor | B6: May 2026 | C6: All StartMonthIdx references count from here
A8: Quarter → Month Index Map
A9: Quarter | B9: Start Month Idx | C9: End Month Idx | D9: # Months | E9: Period
A10: Q2 2026 | B10: 1 | C10: 2 | D10: =C10-B10+1 -> 2 | E10: May–Jun 2026
A11: Q3 2026 | B11: 3 | C11: 5 | D11: =C11-B11+1 -> 3 | E11: Jul–Sep 2026
A12: Q4 2026 | B12: 6 | C12: 8 | D12: =C12-B12+1 -> 3 | E12: Oct–Dec 2026
A13: Q1 2027 | B13: 9 | C13: 11 | D13: =C13-B13+1 -> 3 | E13: Jan–Mar 2027
A14: Q2 2027 | B14: 12 | C14: 14 | D14: =C14-B14+1 -> 3 | E14: Apr–Jun 2027
A15: Q3 2027 | B15: 15 | C15: 17 | D15: =C15-B15+1 -> 3 | E15: Jul–Sep 2027
A16: Q4 2027 | B16: 18 | C16: 20 | D16: =C16-B16+1 -> 3 | E16: Oct–Dec 2027
A17: Q1 2028 | B17: 21 | C17: 23 | D17: =C17-B17+1 -> 3 | E17: Jan–Mar 2028
A18: Q2 2028 | B18: 24 | C18: 26 | D18: =C18-B18+1 -> 3 | E18: Apr–Jun 2028

Sheet Team Roster
A1: Team Roster
A3: # | B3: Name | C3: Role | D3: Status | E3: Start Month Idx | F3: Start Period | G3: Base Monthly (EGP) | H3: Loaded Monthly (EGP) | I3: Notes
A4: 1 | B4: Mohamed Sabry | C4: CEO / Product Owner | D4: Active | E4: 1 | F4: =IFERROR(INDEX(Assumptions!$A$10:$A$18, MATCH(1, (Assumptions!$B$10:$B$18<=E4)*(Assumptions!$C$10:$C$18>=E4), 0)), "—") -> Q2 2026 | G4: 0 | H4: =G4*(1+Assumptions!$B$4) -> 0 | I4: Placeholder salary — to be filled
A5: 2 | B5: Khaled Nehad | C5: CTO | D5: Active | E5: 1 | F5: =IFERROR(INDEX(Assumptions!$A$10:$A$18, MATCH(1, (Assumptions!$B$10:$B$18<=E5)*(Assumptions!$C$10:$C$18>=E5), 0)), "—") -> Q2 2026 | G5: 0 | H5: =G5*(1+Assumptions!$B$4) -> 0 | I5: Placeholder salary — to be filled
A6: 3 | B6: Rodaina Ehabi | C6: Egybell Liaison / Delivery Coord. | D6: Active | E6: 1 | F6: =IFERROR(INDEX(Assumptions!$A$10:$A$18, MATCH(1, (Assumptions!$B$10:$B$18<=E6)*(Assumptions!$C$10:$C$18>=E6), 0)), "—") -> Q2 2026 | G6: 10000 | H6: =G6*(1+Assumptions!$B$4) -> 12000 | I6: Interfaces with Egybell for data collection & sign-off
A7: 4 | B7: Ehab Hafez | C7: UI/UX Developer | D7: Active | E7: 1 | F7: =IFERROR(INDEX(Assumptions!$A$10:$A$18, MATCH(1, (Assumptions!$B$10:$B$18<=E7)*(Assumptions!$C$10:$C$18>=E7), 0)), "—") -> Q2 2026 | G7: 30000 | H7: =G7*(1+Assumptions!$B$4) -> 36000
A8: 5 | B8: TBH — Senior FE Developer | C8: Senior Frontend Developer | D8: To Be Hired | E8: 3 | F8: =IFERROR(INDEX(Assumptions!$A$10:$A$18, MATCH(1, (Assumptions!$B$10:$B$18<=E8)*(Assumptions!$C$10:$C$18>=E8), 0)), "—") -> Q3 2026 | G8: 55000 | H8: =G8*(1+Assumptions!$B$4) -> 66000 | I8: Placeholder rate — adjust once offer is finalised
A9: 6 | B9: TBH — Senior BE Developer | C9: Senior Backend Developer | D9: To Be Hired | E9: 3 | F9: =IFERROR(INDEX(Assumptions!$A$10:$A$18, MATCH(1, (Assumptions!$B$10:$B$18<=E9)*(Assumptions!$C$10:$C$18>=E9), 0)), "—") -> Q3 2026 | G9: 60000 | H9: =G9*(1+Assumptions!$B$4) -> 72000 | I9: Placeholder rate — adjust once offer is finalised
A10: 7 | B10: TBH — QA Engineer | C10: QA / Test Engineer | D10: Placeholder | E10: 4 | F10: =IFERROR(INDEX(Assumptions!$A$10:$A$18, MATCH(1, (Assumptions!$B$10:$B$18<=E10)*(Assumptions!$C$10:$C$18>=E10), 0)), "—") -> Q3 2026 | G10: 30000 | H10: =G10*(1+Assumptions!$B$4) -> 36000 | I10: Placeholder rate
A11: 8 | B11: TBH — DevOps / Cloud Eng. | C11: DevOps & Cloud Engineer | D11: Placeholder | E11: 3 | F11: =IFERROR(INDEX(Assumptions!$A$10:$A$18, MATCH(1, (Assumptions!$B$10:$B$18<=E11)*(Assumptions!$C$10:$C$18>=E11), 0)), "—") -> Q3 2026 | G11: 50000 | H11: =G11*(1+Assumptions!$B$4) -> 60000 | I11: Placeholder rate
A12: 9 | B12: TBH — Mid FE Developer | C12: Mid Frontend Developer | D12: Placeholder | E12: 6 | F12: =IFERROR(INDEX(Assumptions!$A$10:$A$18, MATCH(1, (Assumptions!$B$10:$B$18<=E12)*(Assumptions!$C$10:$C$18>=E12), 0)), "—") -> Q4 2026 | G12: 35000 | H12: =G12*(1+Assumptions!$B$4) -> 42000 | I12: Placeholder rate — needed as scope grows
A13: 10 | B13: TBH — Mid BE Developer | C13: Mid Backend Developer | D13: Placeholder | E13: 6 | F13: =IFERROR(INDEX(Assumptions!$A$10:$A$18, MATCH(1, (Assumptions!$B$10:$B$18<=E13)*(Assumptions!$C$10:$C$18>=E13), 0)), "—") -> Q4 2026 | G13: 38000 | H13: =G13*(1+Assumptions!$B$4) -> 45600 | I13: Placeholder rate — needed as scope grows
A14: 11 | B14: TBH — Business Analyst | C14: Business Analyst | D14: Placeholder | E14: 1 | F14: =IFERROR(INDEX(Assumptions!$A$10:$A$18, MATCH(1, (Assumptions!$B$10:$B$18<=E14)*(Assumptions!$C$10:$C$18>=E14), 0)), "—") -> Q2 2026 | G14: 25000 | H14: =G14*(1+Assumptions!$B$4) -> 30000 | I14: Placeholder rate
A15: 12 | B15: TBH — Project Manager | C15: Project Manager / Scrum | D15: Placeholder | E15: 1 | F15: =IFERROR(INDEX(Assumptions!$A$10:$A$18, MATCH(1, (Assumptions!$B$10:$B$18<=E15)*(Assumptions!$C$10:$C$18>=E15), 0)), "—") -> Q2 2026 | G15: 40000 | H15: =G15*(1+Assumptions!$B$4) -> 48000 | I15: Placeholder rate
B17: TOTAL MONTHLY (FULLY LOADED) | G17: =SUM(G4:G15) -> 373000 | H17: =SUM(H4:H15) -> 447600

Sheet Salary Schedule
A1: Salary Schedule — Quarterly (EGP, fully loaded)
A3: # | B3: Name | C3: Loaded Monthly | D3: Q2 2026 | E3: Q3 2026 | F3: Q4 2026 | G3: Q1 2027 | H3: Q2 2027 | I3: Q3 2027 | J3: Q4 2027 | K3: Q1 2028 | L3: Q2 2028 | M3: Total
A4: 1 | B4: Mohamed Sabry | C4: ='Team Roster'!H4 -> 0 | D4: =MAX(0, MIN(2, 999) - MAX(1, 'Team Roster'!E4) + 1) * C4 -> 0 | E4: =MAX(0, MIN(5, 999) - MAX(3, 'Team Roster'!E4) + 1) * C4 -> 0 | F4: =MAX(0, MIN(8, 999) - MAX(6, 'Team Roster'!E4) + 1) * C4 -> 0 | G4: =MAX(0, MIN(11, 999) - MAX(9, 'Team Roster'!E4) + 1) * C4 -> 0 | H4: =MAX(0, MIN(14, 999) - MAX(12, 'Team Roster'!E4) + 1) * C4 -> 0 | I4: =MAX(0, MIN(17, 999) - MAX(15, 'Team Roster'!E4) + 1) * C4 -> 0 | J4: =MAX(0, MIN(20, 999) - MAX(18, 'Team Roster'!E4) + 1) * C4 -> 0 | K4: =MAX(0, MIN(23, 999) - MAX(21, 'Team Roster'!E4) + 1) * C4 -> 0 | L4: =MAX(0, MIN(26, 999) - MAX(24, 'Team Roster'!E4) + 1) * C4 -> 0 | M4: =SUM(D4:L4) -> 0
A5: 2 | B5: Khaled Nehad | C5: ='Team Roster'!H5 -> 0 | D5: =MAX(0, MIN(2, 999) - MAX(1, 'Team Roster'!E5) + 1) * C5 -> 0 | E5: =MAX(0, MIN(5, 999) - MAX(3, 'Team Roster'!E5) + 1) * C5 -> 0 | F5: =MAX(0, MIN(8, 999) - MAX(6, 'Team Roster'!E5) + 1) * C5 -> 0 | G5: =MAX(0, MIN(11, 999) - MAX(9, 'Team Roster'!E5) + 1) * C5 -> 0 | H5: =MAX(0, MIN(14, 999) - MAX(12, 'Team Roster'!E5) + 1) * C5 -> 0 | I5: =MAX(0, MIN(17, 999) - MAX(15, 'Team Roster'!E5) + 1) * C5 -> 0 | J5: =MAX(0, MIN(20, 999) - MAX(18, 'Team Roster'!E5) + 1) * C5 -> 0 | K5: =MAX(0, MIN(23, 999) - MAX(21, 'Team Roster'!E5) + 1) * C5 -> 0 | L5: =MAX(0, MIN(26, 999) - MAX(24, 'Team Roster'!E5) + 1) * C5 -> 0 | M5: =SUM(D5:L5) -> 0
A6: 3 | B6: Rodaina Ehabi | C6: ='Team Roster'!H6 -> 12000 | D6: =MAX(0, MIN(2, 999) - MAX(1, 'Team Roster'!E6) + 1) * C6 -> 24000 | E6: =MAX(0, MIN(5, 999) - MAX(3, 'Team Roster'!E6) + 1) * C6 -> 36000 | F6: =MAX(0, MIN(8, 999) - MAX(6, 'Team Roster'!E6) + 1) * C6 -> 36000 | G6: =MAX(0, MIN(11, 999) - MAX(9, 'Team Roster'!E6) + 1) * C6 -> 36000 | H6: =MAX(0, MIN(14, 999) - MAX(12, 'Team Roster'!E6) + 1) * C6 -> 36000 | I6: =MAX(0, MIN(17, 999) - MAX(15, 'Team Roster'!E6) + 1) * C6 -> 36000 | J6: =MAX(0, MIN(20, 999) - MAX(18, 'Team Roster'!E6) + 1) * C6 -> 36000 | K6: =MAX(0, MIN(23, 999) - MAX(21, 'Team Roster'!E6) + 1) * C6 -> 36000 | L6: =MAX(0, MIN(26, 999) - MAX(24, 'Team Roster'!E6) + 1) * C6 -> 36000 | M6: =SUM(D6:L6) -> 312000
A7: 4 | B7: Ehab Hafez | C7: ='Team Roster'!H7 -> 36000 | D7: =MAX(0, MIN(2, 999) - MAX(1, 'Team Roster'!E7) + 1) * C7 -> 72000 | E7: =MAX(0, MIN(5, 999) - MAX(3, 'Team Roster'!E7) + 1) * C7 -> 108000 | F7: =MAX(0, MIN(8, 999) - MAX(6, 'Team Roster'!E7) + 1) * C7 -> 108000 | G7: =MAX(0, MIN(11, 999) - MAX(9, 'Team Roster'!E7) + 1) * C7 -> 108000 | H7: =MAX(0, MIN(14, 999) - MAX(12, 'Team Roster'!E7) + 1) * C7 -> 108000 | I7: =MAX(0, MIN(17, 999) - MAX(15, 'Team Roster'!E7) + 1) * C7 -> 108000 | J7: =MAX(0, MIN(20, 999) - MAX(18, 'Team Roster'!E7) + 1) * C7 -> 108000 | K7: =MAX(0, MIN(23, 999) - MAX(21, 'Team Roster'!E7) + 1) * C7 -> 108000 | L7: =MAX(0, MIN(26, 999) - MAX(24, 'Team Roster'!E7) + 1) * C7 -> 108000 | M7: =SUM(D7:L7) -> 936000
A8: 5 | B8: TBH — Senior FE Developer | C8: ='Team Roster'!H8 -> 66000 | D8: =MAX(0, MIN(2, 999) - MAX(1, 'Team Roster'!E8) + 1) * C8 -> 0 | E8: =MAX(0, MIN(5, 999) - MAX(3, 'Team Roster'!E8) + 1) * C8 -> 198000 | F8: =MAX(0, MIN(8, 999) - MAX(6, 'Team Roster'!E8) + 1) * C8 -> 198000 | G8: =MAX(0, MIN(11, 999) - MAX(9, 'Team Roster'!E8) + 1) * C8 -> 198000 | H8: =MAX(0, MIN(14, 999) - MAX(12, 'Team Roster'!E8) + 1) * C8 -> 198000 | I8: =MAX(0, MIN(17, 999) - MAX(15, 'Team Roster'!E8) + 1) * C8 -> 198000 | J8: =MAX(0, MIN(20, 999) - MAX(18, 'Team Roster'!E8) + 1) * C8 -> 198000 | K8: =MAX(0, MIN(23, 999) - MAX(21, 'Team Roster'!E8) + 1) * C8 -> 198000 | L8: =MAX(0, MIN(26, 999) - MAX(24, 'Team Roster'!E8) + 1) * C8 -> 198000 | M8: =SUM(D8:L8) -> 1584000
A9: 6 | B9: TBH — Senior BE Developer | C9: ='Team Roster'!H9 -> 72000 | D9: =MAX(0, MIN(2, 999) - MAX(1, 'Team Roster'!E9) + 1) * C9 -> 0 | E9: =MAX(0, MIN(5, 999) - MAX(3, 'Team Roster'!E9) + 1) * C9 -> 216000 | F9: =MAX(0, MIN(8, 999) - MAX(6, 'Team Roster'!E9) + 1) * C9 -> 216000 | G9: =MAX(0, MIN(11, 999) - MAX(9, 'Team Roster'!E9) + 1) * C9 -> 216000 | H9: =MAX(0, MIN(14, 999) - MAX(12, 'Team Roster'!E9) + 1) * C9 -> 216000 | I9: =MAX(0, MIN(17, 999) - MAX(15, 'Team Roster'!E9) + 1) * C9 -> 216000 | J9: =MAX(0, MIN(20, 999) - MAX(18, 'Team Roster'!E9) + 1) * C9 -> 216000 | K9: =MAX(0, MIN(23, 999) - MAX(21, 'Team Roster'!E9) + 1) * C9 -> 216000 | L9: =MAX(0, MIN(26, 999) - MAX(24, 'Team Roster'!E9) + 1) * C9 -> 216000 | M9: =SUM(D9:L9) -> 1728000
A10: 7 | B10: TBH — QA Engineer | C10: ='Team Roster'!H10 -> 36000 | D10: =MAX(0, MIN(2, 999) - MAX(1, 'Team Roster'!E10) + 1) * C10 -> 0 | E10: =MAX(0, MIN(5, 999) - MAX(3, 'Team Roster'!E10) + 1) * C10 -> 72000 | F10: =MAX(0, MIN(8, 999) - MAX(6, 'Team Roster'!E10) + 1) * C10 -> 108000 | G10: =MAX(0, MIN(11, 999) - MAX(9, 'Team Roster'!E10) + 1) * C10 -> 108000 | H10: =MAX(0, MIN(14, 999) - MAX(12, 'Team Roster'!E10) + 1) * C10 -> 108000 | I10: =MAX(0, MIN(17, 999) - MAX(15, 'Team Roster'!E10) + 1) * C10 -> 108000 | J10: =MAX(0, MIN(20, 999) - MAX(18, 'Team Roster'!E10) + 1) * C10 -> 108000 | K10: =MAX(0, MIN(23, 999) - MAX(21, 'Team Roster'!E10) + 1) * C10 -> 108000 | L10: =MAX(0, MIN(26, 999) - MAX(24, 'Team Roster'!E10) + 1) * C10 -> 108000 | M10: =SUM(D10:L10) -> 828000
A11: 8 | B11: TBH — DevOps / Cloud Eng. | C11: ='Team Roster'!H11 -> 60000 | D11: =MAX(0, MIN(2, 999) - MAX(1, 'Team Roster'!E11) + 1) * C11 -> 0 | E11: =MAX(0, MIN(5, 999) - MAX(3, 'Team Roster'!E11) + 1) * C11 -> 180000 | F11: =MAX(0, MIN(8, 999) - MAX(6, 'Team Roster'!E11) + 1) * C11 -> 180000 | G11: =MAX(0, MIN(11, 999) - MAX(9, 'Team Roster'!E11) + 1) * C11 -> 180000 | H11: =MAX(0, MIN(14, 999) - MAX(12, 'Team Roster'!E11) + 1) * C11 -> 180000 | I11: =MAX(0, MIN(17, 999) - MAX(15, 'Team Roster'!E11) + 1) * C11 -> 180000 | J11: =MAX(0, MIN(20, 999) - MAX(18, 'Team Roster'!E11) + 1) * C11 -> 180000 | K11: =MAX(0, MIN(23, 999) - MAX(21, 'Team Roster'!E11) + 1) * C11 -> 180000 | L11: =MAX(0, MIN(26, 999) - MAX(24, 'Team Roster'!E11) + 1) * C11 -> 180000 | M11: =SUM(D11:L11) -> 1440000
A12: 9 | B12: TBH — Mid FE Developer | C12: ='Team Roster'!H12 -> 42000 | D12: =MAX(0, MIN(2, 999) - MAX(1, 'Team Roster'!E12) + 1) * C12 -> 0 | E12: =MAX(0, MIN(5, 999) - MAX(3, 'Team Roster'!E12) + 1) * C12 -> 0 | F12: =MAX(0, MIN(8, 999) - MAX(6, 'Team Roster'!E12) + 1) * C12 -> 126000 | G12: =MAX(0, MIN(11, 999) - MAX(9, 'Team Roster'!E12) + 1) * C12 -> 126000 | H12: =MAX(0, MIN(14, 999) - MAX(12, 'Team Roster'!E12) + 1) * C12 -> 126000 | I12: =MAX(0, MIN(17, 999) - MAX(15, 'Team Roster'!E12) + 1) * C12 -> 126000 | J12: =MAX(0, MIN(20, 999) - MAX(18, 'Team Roster'!E12) + 1) * C12 -> 126000 | K12: =MAX(0, MIN(23, 999) - MAX(21, 'Team Roster'!E12) + 1) * C12 -> 126000 | L12: =MAX(0, MIN(26, 999) - MAX(24, 'Team Roster'!E12) + 1) * C12 -> 126000 | M12: =SUM(D12:L12) -> 882000
A13: 10 | B13: TBH — Mid BE Developer | C13: ='Team Roster'!H13 -> 45600 | D13: =MAX(0, MIN(2, 999) - MAX(1, 'Team Roster'!E13) + 1) * C13 -> 0 | E13: =MAX(0, MIN(5, 999) - MAX(3, 'Team Roster'!E13) + 1) * C13 -> 0 | F13: =MAX(0, MIN(8, 999) - MAX(6, 'Team Roster'!E13) + 1) * C13 -> 136800 | G13: =MAX(0, MIN(11, 999) - MAX(9, 'Team Roster'!E13) + 1) * C13 -> 136800 | H13: =MAX(0, MIN(14, 999) - MAX(12, 'Team Roster'!E13) + 1) * C13 -> 136800 | I13: =MAX(0, MIN(17, 999) - MAX(15, 'Team Roster'!E13) + 1) * C13 -> 136800 | J13: =MAX(0, MIN(20, 999) - MAX(18, 'Team Roster'!E13) + 1) * C13 -> 136800 | K13: =MAX(0, MIN(23, 999) - MAX(21, 'Team Roster'!E13) + 1) * C13 -> 136800 | L13: =MAX(0, MIN(26, 999) - MAX(24, 'Team Roster'!E13) + 1) * C13 -> 136800 | M13: =SUM(D13:L13) -> 957600
A14: 11 | B14: TBH — Business Analyst | C14: ='Team Roster'!H14 -> 30000 | D14: =MAX(0, MIN(2, 999) - MAX(1, 'Team Roster'!E14) + 1) * C14 -> 60000 | E14: =MAX(0, MIN(5, 999) - MAX(3, 'Team Roster'!E14) + 1) * C14 -> 90000 | F14: =MAX(0, MIN(8, 999) - MAX(6, 'Team Roster'!E14) + 1) * C14 -> 90000 | G14: =MAX(0, MIN(11, 999) - MAX(9, 'Team Roster'!E14) + 1) * C14 -> 90000 | H14: =MAX(0, MIN(14, 999) - MAX(12, 'Team Roster'!E14) + 1) * C14 -> 90000 | I14: =MAX(0, MIN(17, 999) - MAX(15, 'Team Roster'!E14) + 1) * C14 -> 90000 | J14: =MAX(0, MIN(20, 999) - MAX(18, 'Team Roster'!E14) + 1) * C14 -> 90000 | K14: =MAX(0, MIN(23, 999) - MAX(21, 'Team Roster'!E14) + 1) * C14 -> 90000 | L14: =MAX(0, MIN(26, 999) - MAX(24, 'Team Roster'!E14) + 1) * C14 -> 90000 | M14: =SUM(D14:L14) -> 780000
A15: 12 | B15: TBH — Project Manager | C15: ='Team Roster'!H15 -> 48000 | D15: =MAX(0, MIN(2, 999) - MAX(1, 'Team Roster'!E15) + 1) * C15 -> 96000 | E15: =MAX(0, MIN(5, 999) - MAX(3, 'Team Roster'!E15) + 1) * C15 -> 144000 | F15: =MAX(0, MIN(8, 999) - MAX(6, 'Team Roster'!E15) + 1) * C15 -> 144000 | G15: =MAX(0, MIN(11, 999) - MAX(9, 'Team Roster'!E15) + 1) * C15 -> 144000 | H15: =MAX(0, MIN(14, 999) - MAX(12, 'Team Roster'!E15) + 1) * C15 -> 144000 | I15: =MAX(0, MIN(17, 999) - MAX(15, 'Team Roster'!E15) + 1) * C15 -> 144000 | J15: =MAX(0, MIN(20, 999) - MAX(18, 'Team Roster'!E15) + 1) * C15 -> 144000 | K15: =MAX(0, MIN(23, 999) - MAX(21, 'Team Roster'!E15) + 1) * C15 -> 144000 | L15: =MAX(0, MIN(26, 999) - MAX(24, 'Team Roster'!E15) + 1) * C15 -> 144000 | M15: =SUM(D15:L15) -> 1248000
B17: TOTAL SALARIES | C17: =SUM(C4:C15) -> 447600 | D17: =SUM(D4:D15) -> 252000 | E17: =SUM(E4:E15) -> 1044000 | F17: =SUM(F4:F15) -> 1342800 | G17: =SUM(G4:G15) -> 1342800 | H17: =SUM(H4:H15) -> 1342800 | I17: =SUM(I4:I15) -> 1342800 | J17: =SUM(J4:J15) -> 1342800 | ... M17: =SUM(M4:M15) -> 10695600

Sheet Contractors
A1: Contractors & Vendors — Quarterly (EGP)
A3: # | B3: Vendor / Scope | C3: Start Month Idx | D3: Duration (months) | E3: Monthly (EGP) | F3: Q2 2026 | G3: Q3 2026 | H3: Q4 2026 | I3: Q1 2027 | J3: Q2 2027 | K3: Q3 2027 | L3: Q4 2027 | M3: Q1 2028 | N3: Q2 2028 | O3: Total
A4: 1 | B4: Egybell (data collection & sign-off) | C4: 1 | D4: 12 | E4: 0 | F4: =MAX(0, MIN(2, C4+D4-1) - MAX(1, C4) + 1) * E4 -> 0 | G4: =MAX(0, MIN(5, C4+D4-1) - MAX(3, C4) + 1) * E4 -> 0 | H4: =MAX(0, MIN(8, C4+D4-1) - MAX(6, C4) + 1) * E4 -> 0 | I4: =MAX(0, MIN(11, C4+D4-1) - MAX(9, C4) + 1) * E4 -> 0 | J4: =MAX(0, MIN(14, C4+D4-1) - MAX(12, C4) + 1) * E4 -> 0 | K4: =MAX(0, MIN(17, C4+D4-1) - MAX(15, C4) + 1) * E4 -> 0 | L4: =MAX(0, MIN(20, C4+D4-1) - MAX(18, C4) + 1) * E4 -> 0 | M4: =MAX(0, MIN(23, C4+D4-1) - MAX(21, C4) + 1) * E4 -> 0 | N4: =MAX(0, MIN(26, C4+D4-1) - MAX(24, C4) + 1) * E4 -> 0 | O4: =SUM(F4:N4) -> 0
A5: 2 | B5: Specialist UX Review (freelance) | C5: 3 | D5: 2 | E5: 25000 | F5: =MAX(0, MIN(2, C5+D5-1) - MAX(1, C5) + 1) * E5 -> 0 | G5: =MAX(0, MIN(5, C5+D5-1) - MAX(3, C5) + 1) * E5 -> 50000 | H5: =MAX(0, MIN(8, C5+D5-1) - MAX(6, C5) + 1) * E5 -> 0 | I5: =MAX(0, MIN(11, C5+D5-1) - MAX(9, C5) + 1) * E5 -> 0 | J5: =MAX(0, MIN(14, C5+D5-1) - MAX(12, C5) + 1) * E5 -> 0 | K5: =MAX(0, MIN(17, C5+D5-1) - MAX(15, C5) + 1) * E5 -> 0 | L5: =MAX(0, MIN(20, C5+D5-1) - MAX(18, C5) + 1) * E5 -> 0 | M5: =MAX(0, MIN(23, C5+D5-1) - MAX(21, C5) + 1) * E5 -> 0 | N5: =MAX(0, MIN(26, C5+D5-1) - MAX(24, C5) + 1) * E5 -> 0 | O5: =SUM(F5:N5) -> 50000
A6: 3 | B6: Security / Penetration Testing | C6: 9 | D6: 1 | E6: 60000 | F6: =MAX(0, MIN(2, C6+D6-1) - MAX(1, C6) + 1) * E6 -> 0 | G6: =MAX(0, MIN(5, C6+D6-1) - MAX(3, C6) + 1) * E6 -> 0 | H6: =MAX(0, MIN(8, C6+D6-1) - MAX(6, C6) + 1) * E6 -> 0 | I6: =MAX(0, MIN(11, C6+D6-1) - MAX(9, C6) + 1) * E6 -> 60000 | J6: =MAX(0, MIN(14, C6+D6-1) - MAX(12, C6) + 1) * E6 -> 0 | K6: =MAX(0, MIN(17, C6+D6-1) - MAX(15, C6) + 1) * E6 -> 0 | L6: =MAX(0, MIN(20, C6+D6-1) - MAX(18, C6) + 1) * E6 -> 0 | M6: =MAX(0, MIN(23, C6+D6-1) - MAX(21, C6) + 1) * E6 -> 0 | N6: =MAX(0, MIN(26, C6+D6-1) - MAX(24, C6) + 1) * E6 -> 0 | O6: =SUM(F6:N6) -> 60000
A7: 4 | B7: Legal & Compliance (freelance) | C7: 1 | D7: 6 | E7: 15000 | F7: =MAX(0, MIN(2, C7+D7-1) - MAX(1, C7) + 1) * E7 -> 30000 | G7: =MAX(0, MIN(5, C7+D7-1) - MAX(3, C7) + 1) * E7 -> 45000 | H7: =MAX(0, MIN(8, C7+D7-1) - MAX(6, C7) + 1) * E7 -> 15000 | I7: =MAX(0, MIN(11, C7+D7-1) - MAX(9, C7) + 1) * E7 -> 0 | J7: =MAX(0, MIN(14, C7+D7-1) - MAX(12, C7) + 1) * E7 -> 0 | K7: =MAX(0, MIN(17, C7+D7-1) - MAX(15, C7) + 1) * E7 -> 0 | L7: =MAX(0, MIN(20, C7+D7-1) - MAX(18, C7) + 1) * E7 -> 0 | M7: =MAX(0, MIN(23, C7+D7-1) - MAX(21, C7) + 1) * E7 -> 0 | N7: =MAX(0, MIN(26, C7+D7-1) - MAX(24, C7) + 1) * E7 -> 0 | O7: =SUM(F7:N7) -> 90000
B9: TOTAL CONTRACTORS | F9: =SUM(F4:F7) -> 30000 | G9: =SUM(G4:G7) -> 95000 | H9: =SUM(H4:H7) -> 15000 | I9: =SUM(I4:I7) -> 60000 | J9: =SUM(J4:J7) -> 0 | K9: =SUM(K4:K7) -> 0 | L9: =SUM(L4:L7) -> 0 | M9: =SUM(M4:M7) -> 0 | ... O9: =SUM(O4:O7) -> 200000

Sheet Software & Infra
A1: Software & Infrastructure — Recurring Monthly (EGP)
A3: # | B3: Item | C3: Start Month Idx | D3: Monthly (EGP) | E3: Q2 2026 | F3: Q3 2026 | G3: Q4 2026 | H3: Q1 2027 | I3: Q2 2027 | J3: Q3 2027 | K3: Q4 2027 | L3: Q1 2028 | M3: Q2 2028 | N3: Total
A4: 1 | B4: Cloud hosting (AWS/Azure/GCP) | C4: 1 | D4: 12000 | E4: =MAX(0, MIN(2, 999) - MAX(1, C4) + 1) * D4 -> 24000 | F4: =MAX(0, MIN(5, 999) - MAX(3, C4) + 1) * D4 -> 36000 | G4: =MAX(0, MIN(8, 999) - MAX(6, C4) + 1) * D4 -> 36000 | H4: =MAX(0, MIN(11, 999) - MAX(9, C4) + 1) * D4 -> 36000 | I4: =MAX(0, MIN(14, 999) - MAX(12, C4) + 1) * D4 -> 36000 | J4: =MAX(0, MIN(17, 999) - MAX(15, C4) + 1) * D4 -> 36000 | K4: =MAX(0, MIN(20, 999) - MAX(18, C4) + 1) * D4 -> 36000 | L4: =MAX(0, MIN(23, 999) - MAX(21, C4) + 1) * D4 -> 36000 | M4: =MAX(0, MIN(26, 999) - MAX(24, C4) + 1) * D4 -> 36000 | N4: =SUM(E4:M4) -> 312000
A5: 2 | B5: Database & storage | C5: 1 | D5: 5000 | E5: =MAX(0, MIN(2, 999) - MAX(1, C5) + 1) * D5 -> 10000 | F5: =MAX(0, MIN(5, 999) - MAX(3, C5) + 1) * D5 -> 15000 | G5: =MAX(0, MIN(8, 999) - MAX(6, C5) + 1) * D5 -> 15000 | H5: =MAX(0, MIN(11, 999) - MAX(9, C5) + 1) * D5 -> 15000 | I5: =MAX(0, MIN(14, 999) - MAX(12, C5) + 1) * D5 -> 15000 | J5: =MAX(0, MIN(17, 999) - MAX(15, C5) + 1) * D5 -> 15000 | K5: =MAX(0, MIN(20, 999) - MAX(18, C5) + 1) * D5 -> 15000 | L5: =MAX(0, MIN(23, 999) - MAX(21, C5) + 1) * D5 -> 15000 | M5: =MAX(0, MIN(26, 999) - MAX(24, C5) + 1) * D5 -> 15000 | N5: =SUM(E5:M5) -> 130000
A6: 3 | B6: GitHub / GitLab team plan | C6: 1 | D6: 2500 | E6: =MAX(0, MIN(2, 999) - MAX(1, C6) + 1) * D6 -> 5000 | F6: =MAX(0, MIN(5, 999) - MAX(3, C6) + 1) * D6 -> 7500 | G6: =MAX(0, MIN(8, 999) - MAX(6, C6) + 1) * D6 -> 7500 | H6: =MAX(0, MIN(11, 999) - MAX(9, C6) + 1) * D6 -> 7500 | I6: =MAX(0, MIN(14, 999) - MAX(12, C6) + 1) * D6 -> 7500 | J6: =MAX(0, MIN(17, 999) - MAX(15, C6) + 1) * D6 -> 7500 | K6: =MAX(0, MIN(20, 999) - MAX(18, C6) + 1) * D6 -> 7500 | L6: =MAX(0, MIN(23, 999) - MAX(21, C6) + 1) * D6 -> 7500 | M6: =MAX(0, MIN(26, 999) - MAX(24, C6) + 1) * D6 -> 7500 | N6: =SUM(E6:M6) -> 65000
A7: 4 | B7: Figma team licences | C7: 1 | D7: 3500 | E7: =MAX(0, MIN(2, 999) - MAX(1, C7) + 1) * D7 -> 7000 | F7: =MAX(0, MIN(5, 999) - MAX(3, C7) + 1) * D7 -> 10500 | G7: =MAX(0, MIN(8, 999) - MAX(6, C7) + 1) * D7 -> 10500 | H7: =MAX(0, MIN(11, 999) - MAX(9, C7) + 1) * D7 -> 10500 | I7: =MAX(0, MIN(14, 999) - MAX(12, C7) + 1) * D7 -> 10500 | J7: =MAX(0, MIN(17, 999) - MAX(15, C7) + 1) * D7 -> 10500 | K7: =MAX(0, MIN(20, 999) - MAX(18, C7) + 1) * D7 -> 10500 | L7: =MAX(0, MIN(23, 999) - MAX(21, C7) + 1) * D7 -> 10500 | M7: =MAX(0, MIN(26, 999) - MAX(24, C7) + 1) * D7 -> 10500 | N7: =SUM(E7:M7) -> 91000
A8: 5 | B8: Jira / Linear / project tooling | C8: 1 | D8: 2000 | E8: =MAX(0, MIN(2, 999) - MAX(1, C8) + 1) * D8 -> 4000 | F8: =MAX(0, MIN(5, 999) - MAX(3, C8) + 1) * D8 -> 6000 | G8: =MAX(0, MIN(8, 999) - MAX(6, C8) + 1) * D8 -> 6000 | H8: =MAX(0, MIN(11, 999) - MAX(9, C8) + 1) * D8 -> 6000 | I8: =MAX(0, MIN(14, 999) - MAX(12, C8) + 1) * D8 -> 6000 | J8: =MAX(0, MIN(17, 999) - MAX(15, C8) + 1) * D8 -> 6000 | K8: =MAX(0, MIN(20, 999) - MAX(18, C8) + 1) * D8 -> 6000 | L8: =MAX(0, MIN(23, 999) - MAX(21, C8) + 1) * D8 -> 6000 | M8: =MAX(0, MIN(26, 999) - MAX(24, C8) + 1) * D8 -> 6000 | N8: =SUM(E8:M8) -> 52000
A9: 6 | B9: Monitoring & observability (Datadog) | C9: 3 | D9: 4000 | E9: =MAX(0, MIN(2, 999) - MAX(1, C9) + 1) * D9 -> 0 | F9: =MAX(0, MIN(5, 999) - MAX(3, C9) + 1) * D9 -> 12000 | G9: =MAX(0, MIN(8, 999) - MAX(6, C9) + 1) * D9 -> 12000 | H9: =MAX(0, MIN(11, 999) - MAX(9, C9) + 1) * D9 -> 12000 | I9: =MAX(0, MIN(14, 999) - MAX(12, C9) + 1) * D9 -> 12000 | J9: =MAX(0, MIN(17, 999) - MAX(15, C9) + 1) * D9 -> 12000 | K9: =MAX(0, MIN(20, 999) - MAX(18, C9) + 1) * D9 -> 12000 | L9: =MAX(0, MIN(23, 999) - MAX(21, C9) + 1) * D9 -> 12000 | M9: =MAX(0, MIN(26, 999) - MAX(24, C9) + 1) * D9 -> 12000 | N9: =SUM(E9:M9) -> 96000
A10: 7 | B10: Email, chat & productivity (MS365/GW) | C10: 1 | D10: 3000 | E10: =MAX(0, MIN(2, 999) - MAX(1, C10) + 1) * D10 -> 6000 | F10: =MAX(0, MIN(5, 999) - MAX(3, C10) + 1) * D10 -> 9000 | G10: =MAX(0, MIN(8, 999) - MAX(6, C10) + 1) * D10 -> 9000 | H10: =MAX(0, MIN(11, 999) - MAX(9, C10) + 1) * D10 -> 9000 | I10: =MAX(0, MIN(14, 999) - MAX(12, C10) + 1) * D10 -> 9000 | J10: =MAX(0, MIN(17, 999) - MAX(15, C10) + 1) * D10 -> 9000 | K10: =MAX(0, MIN(20, 999) - MAX(18, C10) + 1) * D10 -> 9000 | L10: =MAX(0, MIN(23, 999) - MAX(21, C10) + 1) * D10 -> 9000 | M10: =MAX(0, MIN(26, 999) - MAX(24, C10) + 1) * D10 -> 9000 | N10: =SUM(E10:M10) -> 78000
A11: 8 | B11: Security tools (SSO, secrets) | C11: 1 | D11: 2500 | E11: =MAX(0, MIN(2, 999) - MAX(1, C11) + 1) * D11 -> 5000 | F11: =MAX(0, MIN(5, 999) - MAX(3, C11) + 1) * D11 -> 7500 | G11: =MAX(0, MIN(8, 999) - MAX(6, C11) + 1) * D11 -> 7500 | H11: =MAX(0, MIN(11, 999) - MAX(9, C11) + 1) * D11 -> 7500 | I11: =MAX(0, MIN(14, 999) - MAX(12, C11) + 1) * D11 -> 7500 | J11: =MAX(0, MIN(17, 999) - MAX(15, C11) + 1) * D11 -> 7500 | K11: =MAX(0, MIN(20, 999) - MAX(18, C11) + 1) * D11 -> 7500 | L11: =MAX(0, MIN(23, 999) - MAX(21, C11) + 1) * D11 -> 7500 | M11: =MAX(0, MIN(26, 999) - MAX(24, C11) + 1) * D11 -> 7500 | N11: =SUM(E11:M11) -> 65000
A12: 9 | B12: CI/CD & testing services | C12: 3 | D12: 2000 | E12: =MAX(0, MIN(2, 999) - MAX(1, C12) + 1) * D12 -> 0 | F12: =MAX(0, MIN(5, 999) - MAX(3, C12) + 1) * D12 -> 6000 | G12: =MAX(0, MIN(8, 999) - MAX(6, C12) + 1) * D12 -> 6000 | H12: =MAX(0, MIN(11, 999) - MAX(9, C12) + 1) * D12 -> 6000 | I12: =MAX(0, MIN(14, 999) - MAX(12, C12) + 1) * D12 -> 6000 | J12: =MAX(0, MIN(17, 999) - MAX(15, C12) + 1) * D12 -> 6000 | K12: =MAX(0, MIN(20, 999) - MAX(18, C12) + 1) * D12 -> 6000 | L12: =MAX(0, MIN(23, 999) - MAX(21, C12) + 1) * D12 -> 6000 | M12: =MAX(0, MIN(26, 999) - MAX(24, C12) + 1) * D12 -> 6000 | N12: =SUM(E12:M12) -> 48000
B14: TOTAL SOFTWARE & INFRA | E14: =SUM(E4:E12) -> 61000 | F14: =SUM(F4:F12) -> 109500 | G14: =SUM(G4:G12) -> 109500 | H14: =SUM(H4:H12) -> 109500 | I14: =SUM(I4:I12) -> 109500 | J14: =SUM(J4:J12) -> 109500 | K14: =SUM(K4:K12) -> 109500 | L14: =SUM(L4:L12) -> 109500 | ... N14: =SUM(N4:N12) -> 937000

Sheet Hardware & Setup
A1: Hardware & One-off Setup (EGP)
A3: # | B3: Item | C3: Purchase Month Idx | D3: One-off (EGP) | E3: Q2 2026 | F3: Q3 2026 | G3: Q4 2026 | H3: Q1 2027 | I3: Q2 2027 | J3: Q3 2027 | K3: Q4 2027 | L3: Q1 2028 | M3: Q2 2028 | N3: Total
A4: 1 | B4: Laptops — core team (4) | C4: 1 | D4: 160000 | E4: =IF(AND(C4>=1, C4<=2), D4, 0) -> 160000 | F4: =IF(AND(C4>=3, C4<=5), D4, 0) -> 0 | G4: =IF(AND(C4>=6, C4<=8), D4, 0) -> 0 | H4: =IF(AND(C4>=9, C4<=11), D4, 0) -> 0 | I4: =IF(AND(C4>=12, C4<=14), D4, 0) -> 0 | J4: =IF(AND(C4>=15, C4<=17), D4, 0) -> 0 | K4: =IF(AND(C4>=18, C4<=20), D4, 0) -> 0 | L4: =IF(AND(C4>=21, C4<=23), D4, 0) -> 0 | M4: =IF(AND(C4>=24, C4<=26), D4, 0) -> 0 | N4: =SUM(E4:M4) -> 160000
A5: 2 | B5: Laptops — new hires (2 Senior) | C5: 3 | D5: 80000 | E5: =IF(AND(C5>=1, C5<=2), D5, 0) -> 0 | F5: =IF(AND(C5>=3, C5<=5), D5, 0) -> 80000 | G5: =IF(AND(C5>=6, C5<=8), D5, 0) -> 0 | H5: =IF(AND(C5>=9, C5<=11), D5, 0) -> 0 | I5: =IF(AND(C5>=12, C5<=14), D5, 0) -> 0 | J5: =IF(AND(C5>=15, C5<=17), D5, 0) -> 0 | K5: =IF(AND(C5>=18, C5<=20), D5, 0) -> 0 | L5: =IF(AND(C5>=21, C5<=23), D5, 0) -> 0 | M5: =IF(AND(C5>=24, C5<=26), D5, 0) -> 0 | N5: =SUM(E5:M5) -> 80000
A6: 3 | B6: Laptops — add'l hires (4) | C6: 6 | D6: 160000 | E6: =IF(AND(C6>=1, C6<=2), D6, 0) -> 0 | F6: =IF(AND(C6>=3, C6<=5), D6, 0) -> 0 | G6: =IF(AND(C6>=6, C6<=8), D6, 0) -> 160000 | H6: =IF(AND(C6>=9, C6<=11), D6, 0) -> 0 | I6: =IF(AND(C6>=12, C6<=14), D6, 0) -> 0 | J6: =IF(AND(C6>=15, C6<=17), D6, 0) -> 0 | K6: =IF(AND(C6>=18, C6<=20), D6, 0) -> 0 | L6: =IF(AND(C6>=21, C6<=23), D6, 0) -> 0 | M6: =IF(AND(C6>=24, C6<=26), D6, 0) -> 0 | N6: =SUM(E6:M6) -> 160000
A7: 4 | B7: Monitors & peripherals | C7: 1 | D7: 60000 | E7: =IF(AND(C7>=1, C7<=2), D7, 0) -> 60000 | F7: =IF(AND(C7>=3, C7<=5), D7, 0) -> 0 | G7: =IF(AND(C7>=6, C7<=8), D7, 0) -> 0 | H7: =IF(AND(C7>=9, C7<=11), D7, 0) -> 0 | I7: =IF(AND(C7>=12, C7<=14), D7, 0) -> 0 | J7: =IF(AND(C7>=15, C7<=17), D7, 0) -> 0 | K7: =IF(AND(C7>=18, C7<=20), D7, 0) -> 0 | L7: =IF(AND(C7>=21, C7<=23), D7, 0) -> 0 | M7: =IF(AND(C7>=24, C7<=26), D7, 0) -> 0 | N7: =SUM(E7:M7) -> 60000
A8: 5 | B8: Office / remote setup kit | C8: 1 | D8: 40000 | E8: =IF(AND(C8>=1, C8<=2), D8, 0) -> 40000 | F8: =IF(AND(C8>=3, C8<=5), D8, 0) -> 0 | G8: =IF(AND(C8>=6, C8<=8), D8, 0) -> 0 | H8: =IF(AND(C8>=9, C8<=11), D8, 0) -> 0 | I8: =IF(AND(C8>=12, C8<=14), D8, 0) -> 0 | J8: =IF(AND(C8>=15, C8<=17), D8, 0) -> 0 | K8: =IF(AND(C8>=18, C8<=20), D8, 0) -> 0 | L8: =IF(AND(C8>=21, C8<=23), D8, 0) -> 0 | M8: =IF(AND(C8>=24, C8<=26), D8, 0) -> 0 | N8: =SUM(E8:M8) -> 40000
A9: 6 | B9: Contingency — replacements/expansion | C9: 12 | D9: 50000 | E9: =IF(AND(C9>=1, C9<=2), D9, 0) -> 0 | F9: =IF(AND(C9>=3, C9<=5), D9, 0) -> 0 | G9: =IF(AND(C9>=6, C9<=8), D9, 0) -> 0 | H9: =IF(AND(C9>=9, C9<=11), D9, 0) -> 0 | I9: =IF(AND(C9>=12, C9<=14), D9, 0) -> 50000 | J9: =IF(AND(C9>=15, C9<=17), D9, 0) -> 0 | K9: =IF(AND(C9>=18, C9<=20), D9, 0) -> 0 | L9: =IF(AND(C9>=21, C9<=23), D9, 0) -> 0 | M9: =IF(AND(C9>=24, C9<=26), D9, 0) -> 0 | N9: =SUM(E9:M9) -> 50000
B11: TOTAL HARDWARE & SETUP | E11: =SUM(E4:E9) -> 260000 | F11: =SUM(F4:F9) -> 80000 | G11: =SUM(G4:G9) -> 160000 | H11: =SUM(H4:H9) -> 0 | I11: =SUM(I4:I9) -> 50000 | J11: =SUM(J4:J9) -> 0 | K11: =SUM(K4:K9) -> 0 | L11: =SUM(L4:L9) -> 0 | ... N11: =SUM(N4:N9) -> 550000

Sheet Quarterly Summary
A1: Quarterly Summary — All Categories (EGP)
A3: # | B3: Category | C3: Q2 2026 | D3: Q3 2026 | E3: Q4 2026 | F3: Q1 2027 | G3: Q2 2027 | H3: Q3 2027 | I3: Q4 2027 | J3: Q1 2028 | K3: Q2 2028 | L3: Total
A4: 1 | B4: Salaries & benefits | C4: ='Salary Schedule'!D17 -> 252000 | D4: ='Salary Schedule'!E17 -> 1044000 | E4: ='Salary Schedule'!F17 -> 1342800 | F4: ='Salary Schedule'!G17 -> 1342800 | G4: ='Salary Schedule'!H17 -> 1342800 | H4: ='Salary Schedule'!I17 -> 1342800 | I4: ='Salary Schedule'!J17 -> 1342800 | J4: ='Salary Schedule'!K17 -> 1342800 | K4: ='Salary Schedule'!L17 -> 1342800 | L4: =SUM(C4:K4) -> 10695600
A5: 2 | B5: Contractors / vendors | C5: =Contractors!F9 -> 30000 | D5: =Contractors!G9 -> 95000 | E5: =Contractors!H9 -> 15000 | F5: =Contractors!I9 -> 60000 | G5: =Contractors!J9 -> 0 | H5: =Contractors!K9 -> 0 | I5: =Contractors!L9 -> 0 | J5: =Contractors!M9 -> 0 | K5: =Contractors!N9 -> 0 | L5: =SUM(C5:K5) -> 200000
A6: 3 | B6: Software & infra | C6: ='Software & Infra'!E14 -> 61000 | D6: ='Software & Infra'!F14 -> 109500 | E6: ='Software & Infra'!G14 -> 109500 | F6: ='Software & Infra'!H14 -> 109500 | G6: ='Software & Infra'!I14 -> 109500 | H6: ='Software & Infra'!J14 -> 109500 | I6: ='Software & Infra'!K14 -> 109500 | J6: ='Software & Infra'!L14 -> 109500 | K6: ='Software & Infra'!M14 -> 109500 | L6: =SUM(C6:K6) -> 937000
A7: 4 | B7: Hardware & setup | C7: ='Hardware & Setup'!E11 -> 260000 | D7: ='Hardware & Setup'!F11 -> 80000 | E7: ='Hardware & Setup'!G11 -> 160000 | F7: ='Hardware & Setup'!H11 -> 0 | G7: ='Hardware & Setup'!I11 -> 50000 | H7: ='Hardware & Setup'!J11 -> 0 | I7: ='Hardware & Setup'!K11 -> 0 | J7: ='Hardware & Setup'!L11 -> 0 | K7: ='Hardware & Setup'!M11 -> 0 | L7: =SUM(C7:K7) -> 550000
B9: GRAND TOTAL | C9: =SUM(C4:C7) -> 603000 | D9: =SUM(D4:D7) -> 1328500 | E9: =SUM(E4:E7) -> 1627300 | F9: =SUM(F4:F7) -> 1512300 | G9: =SUM(G4:G7) -> 1502300 | H9: =SUM(H4:H7) -> 1452300 | I9: =SUM(I4:I7) -> 1452300 | J9: =SUM(J4:J7) -> 1452300 | ... L9: =SUM(L4:L7) -> 12382600
B11: Cumulative (running total) | C11: =C9 -> 603000 | D11: =C11+D9 -> 1931500 | E11: =D11+E9 -> 3558800 | F11: =E11+F9 -> 5071100 | G11: =F11+G9 -> 6573400 | H11: =G11+H9 -> 8025700 | I11: =H11+I9 -> 9478000 | J11: =I11+J9 -> 10930300 | K11: =J11+K9 -> 12382600
