Workbook

Sheet Cover
A1: PRAXION HROS — Team Mobilization & Expense Budget
A3: Document | B3: Praxion HROS — Team Mobilization, Salaries & Expenses
A4: Version | B4: v2.0 (USD reporting + native currency preserved)
A5: Prepared | B5: 2026-04-19
A6: Owner | B6: Mohamed Sabry — CEO / Product Owner
A7: Main currency | B7: USD (every number is also shown in native currency)
A8: Native currencies supported | B8: USD, EGP, EUR, GBP, AED, SAR
A9: Horizon | B9: Q2 2026 (May) → Q2 2028 (9 quarters)
A11: Workbook Contents
A12: Assumptions | B12: FX rates per native currency, benefits loading, quarter map
A13: Team Roster | B13: Every role with native + USD loaded monthly cost
A14: Salary Schedule | B14: Quarterly salary cost per person — USD primary, native totals
A15: Contractors | B15: Vendor/freelance engagements by quarter in USD
A16: Software & Infra | B16: Recurring software, cloud & tooling spend (USD)
A17: Hardware & Setup | B17: One-off equipment & setup purchases (USD)
A18: Quarterly Summary | B18: All-category roll-up — USD + native sub-totals + cumulative
A20: Colour Legend
A21: Blue text | B21: Hardcoded input — change to run scenarios
A22: Black text | B22: Formula / calculated value
A23: Green text | B23: Cross-sheet reference
A24: Yellow fill | B24: Placeholder — needs your input
A26: Notes
A27: • USD is the reporting currency. Every monetary number is shown in both native and USD.
A28: • Native salaries stay in local currency (reality of local payroll) — USD derived via FX.
A29: • All FX rates live on the Assumptions tab; change one cell to reprice the entire model.
A30: • Salaries are shown FULLY LOADED (base + benefits loading from Assumptions).
A31: • Start months align to Assumptions!Month_Map — month 1 = May 2026.
A32: • Update only the blue input cells — formulas propagate automatically.

Sheet Assumptions
A1: Assumptions & Inputs
A3: Key | B3: Value | C3: Notes
A4: Benefits loading (% of base) | B4: 0.2 | C4: Social insurance, medical, EOS accrual — adjust to company policy
A5: Annual raise assumption | B5: 0.1 | C5: Not yet applied in schedule — reserved for future version
A6: Month 1 anchor | B6: May 2026 | C6: All StartMonthIdx references count from here
A8: FX Rates (units of Native per 1 USD — edit to reprice model)
A9: Currency Code | B9: Currency Name | C9: Native per USD | D9: USD per Native | E9: Sample (100 native → USD) | F9: Notes
A10: USD | B10: US Dollar | C10: 1 | D10: =1/C10 -> 1 | E10: =100/C10 -> 100 | F10: Base currency
A11: EGP | B11: Egyptian Pound | C11: 50 | D11: =1/C11 -> 0.02 | E11: =100/C11 -> 2 | F11: Edit Column C to update FX rate
A12: EUR | B12: Euro | C12: 0.92 | D12: =1/C12 -> 1.0869565 | E12: =100/C12 -> 108.69565 | F12: Edit Column C to update FX rate
A13: GBP | B13: British Pound | C13: 0.79 | D13: =1/C13 -> 1.2658228 | E13: =100/C13 -> 126.58228 | F13: Edit Column C to update FX rate
A14: AED | B14: UAE Dirham | C14: 3.67 | D14: =1/C14 -> 0.27247956 | E14: =100/C14 -> 27.247956 | F14: Edit Column C to update FX rate
A15: SAR | B15: Saudi Riyal | C15: 3.75 | D15: =1/C15 -> 0.26666667 | E15: =100/C15 -> 26.666667 | F15: Edit Column C to update FX rate
A17: Quarter → Month Index Map
A18: Quarter | B18: Start Month Idx | C18: End Month Idx | D18: # Months | E18: Period
A19: Q2 2026 | B19: 1 | C19: 2 | D19: =C19-B19+1 -> 2 | E19: May–Jun 2026
A20: Q3 2026 | B20: 3 | C20: 5 | D20: =C20-B20+1 -> 3 | E20: Jul–Sep 2026
A21: Q4 2026 | B21: 6 | C21: 8 | D21: =C21-B21+1 -> 3 | E21: Oct–Dec 2026
A22: Q1 2027 | B22: 9 | C22: 11 | D22: =C22-B22+1 -> 3 | E22: Jan–Mar 2027
A23: Q2 2027 | B23: 12 | C23: 14 | D23: =C23-B23+1 -> 3 | E23: Apr–Jun 2027
A24: Q3 2027 | B24: 15 | C24: 17 | D24: =C24-B24+1 -> 3 | E24: Jul–Sep 2027
A25: Q4 2027 | B25: 18 | C25: 20 | D25: =C25-B25+1 -> 3 | E25: Oct–Dec 2027
A26: Q1 2028 | B26: 21 | C26: 23 | D26: =C26-B26+1 -> 3 | E26: Jan–Mar 2028
A27: Q2 2028 | B27: 24 | C27: 26 | D27: =C27-B27+1 -> 3 | E27: Apr–Jun 2028

Sheet Team Roster
A1: Team Roster — Native & USD
A3: # | B3: Name | C3: Role | D3: Status | E3: Start Month Idx | F3: Start Period | G3: Cur | H3: NATIVE (local currency) | J3: USD (reporting) | L3: Notes
H4: Base Monthly | I4: Loaded Monthly | J4: Base Monthly | K4: Loaded Monthly
A5: 1 | B5: Mohamed Sabry | C5: CEO / Product Owner | D5: Active | E5: 1 | F5: =IFERROR(INDEX(Assumptions!$A$19:$A$27, MATCH(1,(Assumptions!$B$19:$B$27<=E5)*(Assumptions!$C$19:$C$27>=E5),0)),"—") -> Q2 2026 | G5: EGP | H5: 0 | I5: =H5*(1+Assumptions!$B$4) -> 0 | J5: =IFERROR(H5/INDEX(Assumptions!$C$10:$C$15,MATCH(G5,Assumptions!$A$10:$A$15,0)),0) -> 0 | K5: =IFERROR(I5/INDEX(Assumptions!$C$10:$C$15,MATCH(G5,Assumptions!$A$10:$A$15,0)),0) -> 0 | L5: Placeholder salary — to be filled
A6: 2 | B6: Khaled Nehad | C6: CTO | D6: Active | E6: 1 | F6: =IFERROR(INDEX(Assumptions!$A$19:$A$27, MATCH(1,(Assumptions!$B$19:$B$27<=E6)*(Assumptions!$C$19:$C$27>=E6),0)),"—") -> Q2 2026 | G6: EGP | H6: 0 | I6: =H6*(1+Assumptions!$B$4) -> 0 | J6: =IFERROR(H6/INDEX(Assumptions!$C$10:$C$15,MATCH(G6,Assumptions!$A$10:$A$15,0)),0) -> 0 | K6: =IFERROR(I6/INDEX(Assumptions!$C$10:$C$15,MATCH(G6,Assumptions!$A$10:$A$15,0)),0) -> 0 | L6: Placeholder salary — to be filled
A7: 3 | B7: Rodaina Ehabi | C7: Egybell Liaison / Delivery Coord. | D7: Active | E7: 1 | F7: =IFERROR(INDEX(Assumptions!$A$19:$A$27, MATCH(1,(Assumptions!$B$19:$B$27<=E7)*(Assumptions!$C$19:$C$27>=E7),0)),"—") -> Q2 2026 | G7: EGP | H7: 10000 | I7: =H7*(1+Assumptions!$B$4) -> 12000 | J7: =IFERROR(H7/INDEX(Assumptions!$C$10:$C$15,MATCH(G7,Assumptions!$A$10:$A$15,0)),0) -> 200 | K7: =IFERROR(I7/INDEX(Assumptions!$C$10:$C$15,MATCH(G7,Assumptions!$A$10:$A$15,0)),0) -> 240 | L7: Interfaces with Egybell for data collection & sign-off
A8: 4 | B8: Ehab Hafez | C8: UI/UX Developer | D8: Active | E8: 1 | F8: =IFERROR(INDEX(Assumptions!$A$19:$A$27, MATCH(1,(Assumptions!$B$19:$B$27<=E8)*(Assumptions!$C$19:$C$27>=E8),0)),"—") -> Q2 2026 | G8: EGP | H8: 30000 | I8: =H8*(1+Assumptions!$B$4) -> 36000 | J8: =IFERROR(H8/INDEX(Assumptions!$C$10:$C$15,MATCH(G8,Assumptions!$A$10:$A$15,0)),0) -> 600 | K8: =IFERROR(I8/INDEX(Assumptions!$C$10:$C$15,MATCH(G8,Assumptions!$A$10:$A$15,0)),0) -> 720
A9: 5 | B9: TBH — Senior FE Developer | C9: Senior Frontend Developer | D9: To Be Hired | E9: 3 | F9: =IFERROR(INDEX(Assumptions!$A$19:$A$27, MATCH(1,(Assumptions!$B$19:$B$27<=E9)*(Assumptions!$C$19:$C$27>=E9),0)),"—") -> Q3 2026 | G9: EGP | H9: 55000 | I9: =H9*(1+Assumptions!$B$4) -> 66000 | J9: =IFERROR(H9/INDEX(Assumptions!$C$10:$C$15,MATCH(G9,Assumptions!$A$10:$A$15,0)),0) -> 1100 | K9: =IFERROR(I9/INDEX(Assumptions!$C$10:$C$15,MATCH(G9,Assumptions!$A$10:$A$15,0)),0) -> 1320 | L9: Placeholder rate — adjust once offer is finalised
A10: 6 | B10: TBH — Senior BE Developer | C10: Senior Backend Developer | D10: To Be Hired | E10: 3 | F10: =IFERROR(INDEX(Assumptions!$A$19:$A$27, MATCH(1,(Assumptions!$B$19:$B$27<=E10)*(Assumptions!$C$19:$C$27>=E10),0)),"—") -> Q3 2026 | G10: EGP | H10: 60000 | I10: =H10*(1+Assumptions!$B$4) -> 72000 | J10: =IFERROR(H10/INDEX(Assumptions!$C$10:$C$15,MATCH(G10,Assumptions!$A$10:$A$15,0)),0) -> 1200 | K10: =IFERROR(I10/INDEX(Assumptions!$C$10:$C$15,MATCH(G10,Assumptions!$A$10:$A$15,0)),0) -> 1440 | L10: Placeholder rate — adjust once offer is finalised
A11: 7 | B11: TBH — QA Engineer | C11: QA / Test Engineer | D11: Placeholder | E11: 4 | F11: =IFERROR(INDEX(Assumptions!$A$19:$A$27, MATCH(1,(Assumptions!$B$19:$B$27<=E11)*(Assumptions!$C$19:$C$27>=E11),0)),"—") -> Q3 2026 | G11: EGP | H11: 30000 | I11: =H11*(1+Assumptions!$B$4) -> 36000 | J11: =IFERROR(H11/INDEX(Assumptions!$C$10:$C$15,MATCH(G11,Assumptions!$A$10:$A$15,0)),0) -> 600 | K11: =IFERROR(I11/INDEX(Assumptions!$C$10:$C$15,MATCH(G11,Assumptions!$A$10:$A$15,0)),0) -> 720 | L11: Placeholder rate
A12: 8 | B12: TBH — DevOps / Cloud Eng. | C12: DevOps & Cloud Engineer | D12: Placeholder | E12: 3 | F12: =IFERROR(INDEX(Assumptions!$A$19:$A$27, MATCH(1,(Assumptions!$B$19:$B$27<=E12)*(Assumptions!$C$19:$C$27>=E12),0)),"—") -> Q3 2026 | G12: EGP | H12: 50000 | I12: =H12*(1+Assumptions!$B$4) -> 60000 | J12: =IFERROR(H12/INDEX(Assumptions!$C$10:$C$15,MATCH(G12,Assumptions!$A$10:$A$15,0)),0) -> 1000 | K12: =IFERROR(I12/INDEX(Assumptions!$C$10:$C$15,MATCH(G12,Assumptions!$A$10:$A$15,0)),0) -> 1200 | L12: Placeholder rate
A13: 9 | B13: TBH — Mid FE Developer | C13: Mid Frontend Developer | D13: Placeholder | E13: 6 | F13: =IFERROR(INDEX(Assumptions!$A$19:$A$27, MATCH(1,(Assumptions!$B$19:$B$27<=E13)*(Assumptions!$C$19:$C$27>=E13),0)),"—") -> Q4 2026 | G13: EGP | H13: 35000 | I13: =H13*(1+Assumptions!$B$4) -> 42000 | J13: =IFERROR(H13/INDEX(Assumptions!$C$10:$C$15,MATCH(G13,Assumptions!$A$10:$A$15,0)),0) -> 700 | K13: =IFERROR(I13/INDEX(Assumptions!$C$10:$C$15,MATCH(G13,Assumptions!$A$10:$A$15,0)),0) -> 840 | L13: Placeholder rate — needed as scope grows
A14: 10 | B14: TBH — Mid BE Developer | C14: Mid Backend Developer | D14: Placeholder | E14: 6 | F14: =IFERROR(INDEX(Assumptions!$A$19:$A$27, MATCH(1,(Assumptions!$B$19:$B$27<=E14)*(Assumptions!$C$19:$C$27>=E14),0)),"—") -> Q4 2026 | G14: EGP | H14: 38000 | I14: =H14*(1+Assumptions!$B$4) -> 45600 | J14: =IFERROR(H14/INDEX(Assumptions!$C$10:$C$15,MATCH(G14,Assumptions!$A$10:$A$15,0)),0) -> 760 | K14: =IFERROR(I14/INDEX(Assumptions!$C$10:$C$15,MATCH(G14,Assumptions!$A$10:$A$15,0)),0) -> 912 | L14: Placeholder rate — needed as scope grows
A15: 11 | B15: TBH — Business Analyst | C15: Business Analyst | D15: Placeholder | E15: 1 | F15: =IFERROR(INDEX(Assumptions!$A$19:$A$27, MATCH(1,(Assumptions!$B$19:$B$27<=E15)*(Assumptions!$C$19:$C$27>=E15),0)),"—") -> Q2 2026 | G15: EGP | H15: 25000 | I15: =H15*(1+Assumptions!$B$4) -> 30000 | J15: =IFERROR(H15/INDEX(Assumptions!$C$10:$C$15,MATCH(G15,Assumptions!$A$10:$A$15,0)),0) -> 500 | K15: =IFERROR(I15/INDEX(Assumptions!$C$10:$C$15,MATCH(G15,Assumptions!$A$10:$A$15,0)),0) -> 600 | L15: Placeholder rate
A16: 12 | B16: TBH — Project Manager | C16: Project Manager / Scrum | D16: Placeholder | E16: 1 | F16: =IFERROR(INDEX(Assumptions!$A$19:$A$27, MATCH(1,(Assumptions!$B$19:$B$27<=E16)*(Assumptions!$C$19:$C$27>=E16),0)),"—") -> Q2 2026 | G16: EGP | H16: 40000 | I16: =H16*(1+Assumptions!$B$4) -> 48000 | J16: =IFERROR(H16/INDEX(Assumptions!$C$10:$C$15,MATCH(G16,Assumptions!$A$10:$A$15,0)),0) -> 800 | K16: =IFERROR(I16/INDEX(Assumptions!$C$10:$C$15,MATCH(G16,Assumptions!$A$10:$A$15,0)),0) -> 960 | L16: Placeholder rate
B18: TOTAL MONTHLY (FULLY LOADED) — USD | K18: =SUM(K5:K16) -> 8952

Sheet Salary Schedule
A1: Salary Schedule — Quarterly (USD, fully loaded)
A3: # | B3: Name | C3: Cur | D3: Loaded USD Monthly | E3: Q2 2026 | F3: Q3 2026 | G3: Q4 2026 | H3: Q1 2027 | I3: Q2 2027 | J3: Q3 2027 | K3: Q4 2027 | L3: Q1 2028 | M3: Q2 2028 | N3: Total
A4: 1 | B4: Mohamed Sabry | C4: ='Team Roster'!G5 -> EGP | D4: ='Team Roster'!K5 -> 0 | E4: =MAX(0, MIN(2, 999) - MAX(1, 'Team Roster'!E5) + 1) * D4 -> 0 | F4: =MAX(0, MIN(5, 999) - MAX(3, 'Team Roster'!E5) + 1) * D4 -> 0 | G4: =MAX(0, MIN(8, 999) - MAX(6, 'Team Roster'!E5) + 1) * D4 -> 0 | H4: =MAX(0, MIN(11, 999) - MAX(9, 'Team Roster'!E5) + 1) * D4 -> 0 | I4: =MAX(0, MIN(14, 999) - MAX(12, 'Team Roster'!E5) + 1) * D4 -> 0 | J4: =MAX(0, MIN(17, 999) - MAX(15, 'Team Roster'!E5) + 1) * D4 -> 0 | K4: =MAX(0, MIN(20, 999) - MAX(18, 'Team Roster'!E5) + 1) * D4 -> 0 | L4: =MAX(0, MIN(23, 999) - MAX(21, 'Team Roster'!E5) + 1) * D4 -> 0 | M4: =MAX(0, MIN(26, 999) - MAX(24, 'Team Roster'!E5) + 1) * D4 -> 0 | N4: =SUM(E4:M4) -> 0
A5: 2 | B5: Khaled Nehad | C5: ='Team Roster'!G6 -> EGP | D5: ='Team Roster'!K6 -> 0 | E5: =MAX(0, MIN(2, 999) - MAX(1, 'Team Roster'!E6) + 1) * D5 -> 0 | F5: =MAX(0, MIN(5, 999) - MAX(3, 'Team Roster'!E6) + 1) * D5 -> 0 | G5: =MAX(0, MIN(8, 999) - MAX(6, 'Team Roster'!E6) + 1) * D5 -> 0 | H5: =MAX(0, MIN(11, 999) - MAX(9, 'Team Roster'!E6) + 1) * D5 -> 0 | I5: =MAX(0, MIN(14, 999) - MAX(12, 'Team Roster'!E6) + 1) * D5 -> 0 | J5: =MAX(0, MIN(17, 999) - MAX(15, 'Team Roster'!E6) + 1) * D5 -> 0 | K5: =MAX(0, MIN(20, 999) - MAX(18, 'Team Roster'!E6) + 1) * D5 -> 0 | L5: =MAX(0, MIN(23, 999) - MAX(21, 'Team Roster'!E6) + 1) * D5 -> 0 | M5: =MAX(0, MIN(26, 999) - MAX(24, 'Team Roster'!E6) + 1) * D5 -> 0 | N5: =SUM(E5:M5) -> 0
A6: 3 | B6: Rodaina Ehabi | C6: ='Team Roster'!G7 -> EGP | D6: ='Team Roster'!K7 -> 240 | E6: =MAX(0, MIN(2, 999) - MAX(1, 'Team Roster'!E7) + 1) * D6 -> 480 | F6: =MAX(0, MIN(5, 999) - MAX(3, 'Team Roster'!E7) + 1) * D6 -> 720 | G6: =MAX(0, MIN(8, 999) - MAX(6, 'Team Roster'!E7) + 1) * D6 -> 720 | H6: =MAX(0, MIN(11, 999) - MAX(9, 'Team Roster'!E7) + 1) * D6 -> 720 | I6: =MAX(0, MIN(14, 999) - MAX(12, 'Team Roster'!E7) + 1) * D6 -> 720 | J6: =MAX(0, MIN(17, 999) - MAX(15, 'Team Roster'!E7) + 1) * D6 -> 720 | K6: =MAX(0, MIN(20, 999) - MAX(18, 'Team Roster'!E7) + 1) * D6 -> 720 | L6: =MAX(0, MIN(23, 999) - MAX(21, 'Team Roster'!E7) + 1) * D6 -> 720 | M6: =MAX(0, MIN(26, 999) - MAX(24, 'Team Roster'!E7) + 1) * D6 -> 720 | N6: =SUM(E6:M6) -> 6240
A7: 4 | B7: Ehab Hafez | C7: ='Team Roster'!G8 -> EGP | D7: ='Team Roster'!K8 -> 720 | E7: =MAX(0, MIN(2, 999) - MAX(1, 'Team Roster'!E8) + 1) * D7 -> 1440 | F7: =MAX(0, MIN(5, 999) - MAX(3, 'Team Roster'!E8) + 1) * D7 -> 2160 | G7: =MAX(0, MIN(8, 999) - MAX(6, 'Team Roster'!E8) + 1) * D7 -> 2160 | H7: =MAX(0, MIN(11, 999) - MAX(9, 'Team Roster'!E8) + 1) * D7 -> 2160 | I7: =MAX(0, MIN(14, 999) - MAX(12, 'Team Roster'!E8) + 1) * D7 -> 2160 | J7: =MAX(0, MIN(17, 999) - MAX(15, 'Team Roster'!E8) + 1) * D7 -> 2160 | K7: =MAX(0, MIN(20, 999) - MAX(18, 'Team Roster'!E8) + 1) * D7 -> 2160 | L7: =MAX(0, MIN(23, 999) - MAX(21, 'Team Roster'!E8) + 1) * D7 -> 2160 | M7: =MAX(0, MIN(26, 999) - MAX(24, 'Team Roster'!E8) + 1) * D7 -> 2160 | N7: =SUM(E7:M7) -> 18720
A8: 5 | B8: TBH — Senior FE Developer | C8: ='Team Roster'!G9 -> EGP | D8: ='Team Roster'!K9 -> 1320 | E8: =MAX(0, MIN(2, 999) - MAX(1, 'Team Roster'!E9) + 1) * D8 -> 0 | F8: =MAX(0, MIN(5, 999) - MAX(3, 'Team Roster'!E9) + 1) * D8 -> 3960 | G8: =MAX(0, MIN(8, 999) - MAX(6, 'Team Roster'!E9) + 1) * D8 -> 3960 | H8: =MAX(0, MIN(11, 999) - MAX(9, 'Team Roster'!E9) + 1) * D8 -> 3960 | I8: =MAX(0, MIN(14, 999) - MAX(12, 'Team Roster'!E9) + 1) * D8 -> 3960 | J8: =MAX(0, MIN(17, 999) - MAX(15, 'Team Roster'!E9) + 1) * D8 -> 3960 | K8: =MAX(0, MIN(20, 999) - MAX(18, 'Team Roster'!E9) + 1) * D8 -> 3960 | L8: =MAX(0, MIN(23, 999) - MAX(21, 'Team Roster'!E9) + 1) * D8 -> 3960 | M8: =MAX(0, MIN(26, 999) - MAX(24, 'Team Roster'!E9) + 1) * D8 -> 3960 | N8: =SUM(E8:M8) -> 31680
A9: 6 | B9: TBH — Senior BE Developer | C9: ='Team Roster'!G10 -> EGP | D9: ='Team Roster'!K10 -> 1440 | E9: =MAX(0, MIN(2, 999) - MAX(1, 'Team Roster'!E10) + 1) * D9 -> 0 | F9: =MAX(0, MIN(5, 999) - MAX(3, 'Team Roster'!E10) + 1) * D9 -> 4320 | G9: =MAX(0, MIN(8, 999) - MAX(6, 'Team Roster'!E10) + 1) * D9 -> 4320 | H9: =MAX(0, MIN(11, 999) - MAX(9, 'Team Roster'!E10) + 1) * D9 -> 4320 | I9: =MAX(0, MIN(14, 999) - MAX(12, 'Team Roster'!E10) + 1) * D9 -> 4320 | J9: =MAX(0, MIN(17, 999) - MAX(15, 'Team Roster'!E10) + 1) * D9 -> 4320 | K9: =MAX(0, MIN(20, 999) - MAX(18, 'Team Roster'!E10) + 1) * D9 -> 4320 | L9: =MAX(0, MIN(23, 999) - MAX(21, 'Team Roster'!E10) + 1) * D9 -> 4320 | M9: =MAX(0, MIN(26, 999) - MAX(24, 'Team Roster'!E10) + 1) * D9 -> 4320 | N9: =SUM(E9:M9) -> 34560
A10: 7 | B10: TBH — QA Engineer | C10: ='Team Roster'!G11 -> EGP | D10: ='Team Roster'!K11 -> 720 | E10: =MAX(0, MIN(2, 999) - MAX(1, 'Team Roster'!E11) + 1) * D10 -> 0 | F10: =MAX(0, MIN(5, 999) - MAX(3, 'Team Roster'!E11) + 1) * D10 -> 1440 | G10: =MAX(0, MIN(8, 999) - MAX(6, 'Team Roster'!E11) + 1) * D10 -> 2160 | H10: =MAX(0, MIN(11, 999) - MAX(9, 'Team Roster'!E11) + 1) * D10 -> 2160 | I10: =MAX(0, MIN(14, 999) - MAX(12, 'Team Roster'!E11) + 1) * D10 -> 2160 | J10: =MAX(0, MIN(17, 999) - MAX(15, 'Team Roster'!E11) + 1) * D10 -> 2160 | K10: =MAX(0, MIN(20, 999) - MAX(18, 'Team Roster'!E11) + 1) * D10 -> 2160 | L10: =MAX(0, MIN(23, 999) - MAX(21, 'Team Roster'!E11) + 1) * D10 -> 2160 | M10: =MAX(0, MIN(26, 999) - MAX(24, 'Team Roster'!E11) + 1) * D10 -> 2160 | N10: =SUM(E10:M10) -> 16560
A11: 8 | B11: TBH — DevOps / Cloud Eng. | C11: ='Team Roster'!G12 -> EGP | D11: ='Team Roster'!K12 -> 1200 | E11: =MAX(0, MIN(2, 999) - MAX(1, 'Team Roster'!E12) + 1) * D11 -> 0 | F11: =MAX(0, MIN(5, 999) - MAX(3, 'Team Roster'!E12) + 1) * D11 -> 3600 | G11: =MAX(0, MIN(8, 999) - MAX(6, 'Team Roster'!E12) + 1) * D11 -> 3600 | H11: =MAX(0, MIN(11, 999) - MAX(9, 'Team Roster'!E12) + 1) * D11 -> 3600 | I11: =MAX(0, MIN(14, 999) - MAX(12, 'Team Roster'!E12) + 1) * D11 -> 3600 | J11: =MAX(0, MIN(17, 999) - MAX(15, 'Team Roster'!E12) + 1) * D11 -> 3600 | K11: =MAX(0, MIN(20, 999) - MAX(18, 'Team Roster'!E12) + 1) * D11 -> 3600 | L11: =MAX(0, MIN(23, 999) - MAX(21, 'Team Roster'!E12) + 1) * D11 -> 3600 | M11: =MAX(0, MIN(26, 999) - MAX(24, 'Team Roster'!E12) + 1) * D11 -> 3600 | N11: =SUM(E11:M11) -> 28800
A12: 9 | B12: TBH — Mid FE Developer | C12: ='Team Roster'!G13 -> EGP | D12: ='Team Roster'!K13 -> 840 | E12: =MAX(0, MIN(2, 999) - MAX(1, 'Team Roster'!E13) + 1) * D12 -> 0 | F12: =MAX(0, MIN(5, 999) - MAX(3, 'Team Roster'!E13) + 1) * D12 -> 0 | G12: =MAX(0, MIN(8, 999) - MAX(6, 'Team Roster'!E13) + 1) * D12 -> 2520 | H12: =MAX(0, MIN(11, 999) - MAX(9, 'Team Roster'!E13) + 1) * D12 -> 2520 | I12: =MAX(0, MIN(14, 999) - MAX(12, 'Team Roster'!E13) + 1) * D12 -> 2520 | J12: =MAX(0, MIN(17, 999) - MAX(15, 'Team Roster'!E13) + 1) * D12 -> 2520 | K12: =MAX(0, MIN(20, 999) - MAX(18, 'Team Roster'!E13) + 1) * D12 -> 2520 | L12: =MAX(0, MIN(23, 999) - MAX(21, 'Team Roster'!E13) + 1) * D12 -> 2520 | M12: =MAX(0, MIN(26, 999) - MAX(24, 'Team Roster'!E13) + 1) * D12 -> 2520 | N12: =SUM(E12:M12) -> 17640
A13: 10 | B13: TBH — Mid BE Developer | C13: ='Team Roster'!G14 -> EGP | D13: ='Team Roster'!K14 -> 912 | E13: =MAX(0, MIN(2, 999) - MAX(1, 'Team Roster'!E14) + 1) * D13 -> 0 | F13: =MAX(0, MIN(5, 999) - MAX(3, 'Team Roster'!E14) + 1) * D13 -> 0 | G13: =MAX(0, MIN(8, 999) - MAX(6, 'Team Roster'!E14) + 1) * D13 -> 2736 | H13: =MAX(0, MIN(11, 999) - MAX(9, 'Team Roster'!E14) + 1) * D13 -> 2736 | I13: =MAX(0, MIN(14, 999) - MAX(12, 'Team Roster'!E14) + 1) * D13 -> 2736 | J13: =MAX(0, MIN(17, 999) - MAX(15, 'Team Roster'!E14) + 1) * D13 -> 2736 | K13: =MAX(0, MIN(20, 999) - MAX(18, 'Team Roster'!E14) + 1) * D13 -> 2736 | L13: =MAX(0, MIN(23, 999) - MAX(21, 'Team Roster'!E14) + 1) * D13 -> 2736 | M13: =MAX(0, MIN(26, 999) - MAX(24, 'Team Roster'!E14) + 1) * D13 -> 2736 | N13: =SUM(E13:M13) -> 19152
A14: 11 | B14: TBH — Business Analyst | C14: ='Team Roster'!G15 -> EGP | D14: ='Team Roster'!K15 -> 600 | E14: =MAX(0, MIN(2, 999) - MAX(1, 'Team Roster'!E15) + 1) * D14 -> 1200 | F14: =MAX(0, MIN(5, 999) - MAX(3, 'Team Roster'!E15) + 1) * D14 -> 1800 | G14: =MAX(0, MIN(8, 999) - MAX(6, 'Team Roster'!E15) + 1) * D14 -> 1800 | H14: =MAX(0, MIN(11, 999) - MAX(9, 'Team Roster'!E15) + 1) * D14 -> 1800 | I14: =MAX(0, MIN(14, 999) - MAX(12, 'Team Roster'!E15) + 1) * D14 -> 1800 | J14: =MAX(0, MIN(17, 999) - MAX(15, 'Team Roster'!E15) + 1) * D14 -> 1800 | K14: =MAX(0, MIN(20, 999) - MAX(18, 'Team Roster'!E15) + 1) * D14 -> 1800 | L14: =MAX(0, MIN(23, 999) - MAX(21, 'Team Roster'!E15) + 1) * D14 -> 1800 | M14: =MAX(0, MIN(26, 999) - MAX(24, 'Team Roster'!E15) + 1) * D14 -> 1800 | N14: =SUM(E14:M14) -> 15600
A15: 12 | B15: TBH — Project Manager | C15: ='Team Roster'!G16 -> EGP | D15: ='Team Roster'!K16 -> 960 | E15: =MAX(0, MIN(2, 999) - MAX(1, 'Team Roster'!E16) + 1) * D15 -> 1920 | F15: =MAX(0, MIN(5, 999) - MAX(3, 'Team Roster'!E16) + 1) * D15 -> 2880 | G15: =MAX(0, MIN(8, 999) - MAX(6, 'Team Roster'!E16) + 1) * D15 -> 2880 | H15: =MAX(0, MIN(11, 999) - MAX(9, 'Team Roster'!E16) + 1) * D15 -> 2880 | I15: =MAX(0, MIN(14, 999) - MAX(12, 'Team Roster'!E16) + 1) * D15 -> 2880 | J15: =MAX(0, MIN(17, 999) - MAX(15, 'Team Roster'!E16) + 1) * D15 -> 2880 | K15: =MAX(0, MIN(20, 999) - MAX(18, 'Team Roster'!E16) + 1) * D15 -> 2880 | L15: =MAX(0, MIN(23, 999) - MAX(21, 'Team Roster'!E16) + 1) * D15 -> 2880 | M15: =MAX(0, MIN(26, 999) - MAX(24, 'Team Roster'!E16) + 1) * D15 -> 2880 | N15: =SUM(E15:M15) -> 24960
B17: TOTAL SALARIES (USD) | D17: =SUM(D4:D15) -> 8952 | E17: =SUM(E4:E15) -> 5040 | F17: =SUM(F4:F15) -> 20880 | G17: =SUM(G4:G15) -> 26856 | H17: =SUM(H4:H15) -> 26856 | I17: =SUM(I4:I15) -> 26856 | J17: =SUM(J4:J15) -> 26856 | K17: =SUM(K4:K15) -> 26856 | ... N17: =SUM(N4:N15) -> 213912
A19: Native-currency sub-totals (per-quarter total in the local currency of the payee)
B20: Currency | D20: Loaded Monthly (native) | E20: Q2 2026 | F20: Q3 2026 | G20: Q4 2026 | H20: Q1 2027 | I20: Q2 2027 | J20: Q3 2027 | K20: Q4 2027 | L20: Q1 2028 | M20: Q2 2028 | N20: Total
B21: EGP | D21: =SUMPRODUCT(('Team Roster'!G5:G16="EGP")*('Team Roster'!I5:I16)) -> 447600 | E21: =SUMPRODUCT(('Team Roster'!$G$5:$G$16="EGP")*('Team Roster'!$I$5:$I$16)*((2>='Team Roster'!$E$5:$E$16)*(2-IF(1>'Team Roster'!$E$5:$E$16,1,'Team Roster'!$E$5:$E$16)+1))) -> 252000 | F21: =SUMPRODUCT(('Team Roster'!$G$5:$G$16="EGP")*('Team Roster'!$I$5:$I$16)*((5>='Team Roster'!$E$5:$E$16)*(5-IF(3>'Team Roster'!$E$5:$E$16,3,'Team Roster'!$E$5:$E$16)+1))) -> 1044000 | G21: =SUMPRODUCT(('Team Roster'!$G$5:$G$16="EGP")*('Team Roster'!$I$5:$I$16)*((8>='Team Roster'!$E$5:$E$16)*(8-IF(6>'Team Roster'!$E$5:$E$16,6,'Team Roster'!$E$5:$E$16)+1))) -> 1342800 | H21: =SUMPRODUCT(('Team Roster'!$G$5:$G$16="EGP")*('Team Roster'!$I$5:$I$16)*((11>='Team Roster'!$E$5:$E$16)*(11-IF(9>'Team Roster'!$E$5:$E$16,9,'Team Roster'!$E$5:$E$16)+1))) -> 1342800 | I21: =SUMPRODUCT(('Team Roster'!$G$5:$G$16="EGP")*('Team Roster'!$I$5:$I$16)*((14>='Team Roster'!$E$5:$E$16)*(14-IF(12>'Team Roster'!$E$5:$E$16,12,'Team Roster'!$E$5:$E$16)+1))) -> 1342800 | J21: =SUMPRODUCT(('Team Roster'!$G$5:$G$16="EGP")*('Team Roster'!$I$5:$I$16)*((17>='Team Roster'!$E$5:$E$16)*(17-IF(15>'Team Roster'!$E$5:$E$16,15,'Team Roster'!$E$5:$E$16)+1))) -> 1342800 | K21: =SUMPRODUCT(('Team Roster'!$G$5:$G$16="EGP")*('Team Roster'!$I$5:$I$16)*((20>='Team Roster'!$E$5:$E$16)*(20-IF(18>'Team Roster'!$E$5:$E$16,18,'Team Roster'!$E$5:$E$16)+1))) -> 1342800 | L21: =SUMPRODUCT(('Team Roster'!$G$5:$G$16="EGP")*('Team Roster'!$I$5:$I$16)*((23>='Team Roster'!$E$5:$E$16)*(23-IF(21>'Team Roster'!$E$5:$E$16,21,'Team Roster'!$E$5:$E$16)+1))) -> 1342800 | M21: =SUMPRODUCT(('Team Roster'!$G$5:$G$16="EGP")*('Team Roster'!$I$5:$I$16)*((26>='Team Roster'!$E$5:$E$16)*(26-IF(24>'Team Roster'!$E$5:$E$16,24,'Team Roster'!$E$5:$E$16)+1))) -> 1342800 | N21: =SUM(E21:M21) -> 10695600

Sheet Contractors
A1: Contractors & Vendors — Quarterly (USD)
A3: # | B3: Vendor / Scope | C3: Start Month Idx | D3: Duration (months) | E3: Cur | F3: Monthly Native | G3: Monthly USD | H3: Q2 2026 | I3: Q3 2026 | J3: Q4 2026 | K3: Q1 2027 | L3: Q2 2027 | M3: Q3 2027 | N3: Q4 2027 | O3: Q1 2028 | P3: Q2 2028 | Q3: Total USD
A4: 1 | B4: Egybell (data collection & sign-off) | C4: 1 | D4: 12 | E4: EGP | F4: 0 | G4: =IFERROR(F4/INDEX(Assumptions!$C$10:$C$15,MATCH(E4,Assumptions!$A$10:$A$15,0)),0) -> 0 | H4: =MAX(0, MIN(2, C4+D4-1) - MAX(1, C4) + 1) * G4 -> 0 | I4: =MAX(0, MIN(5, C4+D4-1) - MAX(3, C4) + 1) * G4 -> 0 | J4: =MAX(0, MIN(8, C4+D4-1) - MAX(6, C4) + 1) * G4 -> 0 | K4: =MAX(0, MIN(11, C4+D4-1) - MAX(9, C4) + 1) * G4 -> 0 | L4: =MAX(0, MIN(14, C4+D4-1) - MAX(12, C4) + 1) * G4 -> 0 | M4: =MAX(0, MIN(17, C4+D4-1) - MAX(15, C4) + 1) * G4 -> 0 | N4: =MAX(0, MIN(20, C4+D4-1) - MAX(18, C4) + 1) * G4 -> 0 | O4: =MAX(0, MIN(23, C4+D4-1) - MAX(21, C4) + 1) * G4 -> 0 | P4: =MAX(0, MIN(26, C4+D4-1) - MAX(24, C4) + 1) * G4 -> 0 | Q4: =SUM(H4:P4) -> 0
A5: 2 | B5: Specialist UX Review (freelance) | C5: 3 | D5: 2 | E5: EGP | F5: 25000 | G5: =IFERROR(F5/INDEX(Assumptions!$C$10:$C$15,MATCH(E5,Assumptions!$A$10:$A$15,0)),0) -> 500 | H5: =MAX(0, MIN(2, C5+D5-1) - MAX(1, C5) + 1) * G5 -> 0 | I5: =MAX(0, MIN(5, C5+D5-1) - MAX(3, C5) + 1) * G5 -> 1000 | J5: =MAX(0, MIN(8, C5+D5-1) - MAX(6, C5) + 1) * G5 -> 0 | K5: =MAX(0, MIN(11, C5+D5-1) - MAX(9, C5) + 1) * G5 -> 0 | L5: =MAX(0, MIN(14, C5+D5-1) - MAX(12, C5) + 1) * G5 -> 0 | M5: =MAX(0, MIN(17, C5+D5-1) - MAX(15, C5) + 1) * G5 -> 0 | N5: =MAX(0, MIN(20, C5+D5-1) - MAX(18, C5) + 1) * G5 -> 0 | O5: =MAX(0, MIN(23, C5+D5-1) - MAX(21, C5) + 1) * G5 -> 0 | P5: =MAX(0, MIN(26, C5+D5-1) - MAX(24, C5) + 1) * G5 -> 0 | Q5: =SUM(H5:P5) -> 1000
A6: 3 | B6: Security / Penetration Testing | C6: 9 | D6: 1 | E6: USD | F6: 2500 | G6: =IFERROR(F6/INDEX(Assumptions!$C$10:$C$15,MATCH(E6,Assumptions!$A$10:$A$15,0)),0) -> 2500 | H6: =MAX(0, MIN(2, C6+D6-1) - MAX(1, C6) + 1) * G6 -> 0 | I6: =MAX(0, MIN(5, C6+D6-1) - MAX(3, C6) + 1) * G6 -> 0 | J6: =MAX(0, MIN(8, C6+D6-1) - MAX(6, C6) + 1) * G6 -> 0 | K6: =MAX(0, MIN(11, C6+D6-1) - MAX(9, C6) + 1) * G6 -> 2500 | L6: =MAX(0, MIN(14, C6+D6-1) - MAX(12, C6) + 1) * G6 -> 0 | M6: =MAX(0, MIN(17, C6+D6-1) - MAX(15, C6) + 1) * G6 -> 0 | N6: =MAX(0, MIN(20, C6+D6-1) - MAX(18, C6) + 1) * G6 -> 0 | O6: =MAX(0, MIN(23, C6+D6-1) - MAX(21, C6) + 1) * G6 -> 0 | P6: =MAX(0, MIN(26, C6+D6-1) - MAX(24, C6) + 1) * G6 -> 0 | Q6: =SUM(H6:P6) -> 2500
A7: 4 | B7: Legal & Compliance (freelance) | C7: 1 | D7: 6 | E7: EGP | F7: 15000 | G7: =IFERROR(F7/INDEX(Assumptions!$C$10:$C$15,MATCH(E7,Assumptions!$A$10:$A$15,0)),0) -> 300 | H7: =MAX(0, MIN(2, C7+D7-1) - MAX(1, C7) + 1) * G7 -> 600 | I7: =MAX(0, MIN(5, C7+D7-1) - MAX(3, C7) + 1) * G7 -> 900 | J7: =MAX(0, MIN(8, C7+D7-1) - MAX(6, C7) + 1) * G7 -> 300 | K7: =MAX(0, MIN(11, C7+D7-1) - MAX(9, C7) + 1) * G7 -> 0 | L7: =MAX(0, MIN(14, C7+D7-1) - MAX(12, C7) + 1) * G7 -> 0 | M7: =MAX(0, MIN(17, C7+D7-1) - MAX(15, C7) + 1) * G7 -> 0 | N7: =MAX(0, MIN(20, C7+D7-1) - MAX(18, C7) + 1) * G7 -> 0 | O7: =MAX(0, MIN(23, C7+D7-1) - MAX(21, C7) + 1) * G7 -> 0 | P7: =MAX(0, MIN(26, C7+D7-1) - MAX(24, C7) + 1) * G7 -> 0 | Q7: =SUM(H7:P7) -> 1800
B9: TOTAL CONTRACTORS (USD) | G9: =SUM(G4:G7) -> 3300 | H9: =SUM(H4:H7) -> 600 | I9: =SUM(I4:I7) -> 1900 | J9: =SUM(J4:J7) -> 300 | K9: =SUM(K4:K7) -> 2500 | L9: =SUM(L4:L7) -> 0 | M9: =SUM(M4:M7) -> 0 | N9: =SUM(N4:N7) -> 0 | ... Q9: =SUM(Q4:Q7) -> 5300

Sheet Software & Infra
A1: Software & Infrastructure — Recurring Monthly (USD)
A3: # | B3: Item | C3: Start Month Idx | D3: Cur | E3: Monthly Native | F3: Monthly USD | G3: Q2 2026 | H3: Q3 2026 | I3: Q4 2026 | J3: Q1 2027 | K3: Q2 2027 | L3: Q3 2027 | M3: Q4 2027 | N3: Q1 2028 | O3: Q2 2028 | P3: Total USD
A4: 1 | B4: Cloud hosting (AWS/Azure/GCP) | C4: 1 | D4: USD | E4: 400 | F4: =IFERROR(E4/INDEX(Assumptions!$C$10:$C$15,MATCH(D4,Assumptions!$A$10:$A$15,0)),0) -> 400 | G4: =MAX(0, MIN(2, 999) - MAX(1, C4) + 1) * F4 -> 800 | H4: =MAX(0, MIN(5, 999) - MAX(3, C4) + 1) * F4 -> 1200 | I4: =MAX(0, MIN(8, 999) - MAX(6, C4) + 1) * F4 -> 1200 | J4: =MAX(0, MIN(11, 999) - MAX(9, C4) + 1) * F4 -> 1200 | K4: =MAX(0, MIN(14, 999) - MAX(12, C4) + 1) * F4 -> 1200 | L4: =MAX(0, MIN(17, 999) - MAX(15, C4) + 1) * F4 -> 1200 | M4: =MAX(0, MIN(20, 999) - MAX(18, C4) + 1) * F4 -> 1200 | N4: =MAX(0, MIN(23, 999) - MAX(21, C4) + 1) * F4 -> 1200 | O4: =MAX(0, MIN(26, 999) - MAX(24, C4) + 1) * F4 -> 1200 | P4: =SUM(G4:O4) -> 10400
A5: 2 | B5: Database & storage | C5: 1 | D5: USD | E5: 150 | F5: =IFERROR(E5/INDEX(Assumptions!$C$10:$C$15,MATCH(D5,Assumptions!$A$10:$A$15,0)),0) -> 150 | G5: =MAX(0, MIN(2, 999) - MAX(1, C5) + 1) * F5 -> 300 | H5: =MAX(0, MIN(5, 999) - MAX(3, C5) + 1) * F5 -> 450 | I5: =MAX(0, MIN(8, 999) - MAX(6, C5) + 1) * F5 -> 450 | J5: =MAX(0, MIN(11, 999) - MAX(9, C5) + 1) * F5 -> 450 | K5: =MAX(0, MIN(14, 999) - MAX(12, C5) + 1) * F5 -> 450 | L5: =MAX(0, MIN(17, 999) - MAX(15, C5) + 1) * F5 -> 450 | M5: =MAX(0, MIN(20, 999) - MAX(18, C5) + 1) * F5 -> 450 | N5: =MAX(0, MIN(23, 999) - MAX(21, C5) + 1) * F5 -> 450 | O5: =MAX(0, MIN(26, 999) - MAX(24, C5) + 1) * F5 -> 450 | P5: =SUM(G5:O5) -> 3900
A6: 3 | B6: GitHub / GitLab team plan | C6: 1 | D6: USD | E6: 50 | F6: =IFERROR(E6/INDEX(Assumptions!$C$10:$C$15,MATCH(D6,Assumptions!$A$10:$A$15,0)),0) -> 50 | G6: =MAX(0, MIN(2, 999) - MAX(1, C6) + 1) * F6 -> 100 | H6: =MAX(0, MIN(5, 999) - MAX(3, C6) + 1) * F6 -> 150 | I6: =MAX(0, MIN(8, 999) - MAX(6, C6) + 1) * F6 -> 150 | J6: =MAX(0, MIN(11, 999) - MAX(9, C6) + 1) * F6 -> 150 | K6: =MAX(0, MIN(14, 999) - MAX(12, C6) + 1) * F6 -> 150 | L6: =MAX(0, MIN(17, 999) - MAX(15, C6) + 1) * F6 -> 150 | M6: =MAX(0, MIN(20, 999) - MAX(18, C6) + 1) * F6 -> 150 | N6: =MAX(0, MIN(23, 999) - MAX(21, C6) + 1) * F6 -> 150 | O6: =MAX(0, MIN(26, 999) - MAX(24, C6) + 1) * F6 -> 150 | P6: =SUM(G6:O6) -> 1300
A7: 4 | B7: Figma team licences | C7: 1 | D7: USD | E7: 100 | F7: =IFERROR(E7/INDEX(Assumptions!$C$10:$C$15,MATCH(D7,Assumptions!$A$10:$A$15,0)),0) -> 100 | G7: =MAX(0, MIN(2, 999) - MAX(1, C7) + 1) * F7 -> 200 | H7: =MAX(0, MIN(5, 999) - MAX(3, C7) + 1) * F7 -> 300 | I7: =MAX(0, MIN(8, 999) - MAX(6, C7) + 1) * F7 -> 300 | J7: =MAX(0, MIN(11, 999) - MAX(9, C7) + 1) * F7 -> 300 | K7: =MAX(0, MIN(14, 999) - MAX(12, C7) + 1) * F7 -> 300 | L7: =MAX(0, MIN(17, 999) - MAX(15, C7) + 1) * F7 -> 300 | M7: =MAX(0, MIN(20, 999) - MAX(18, C7) + 1) * F7 -> 300 | N7: =MAX(0, MIN(23, 999) - MAX(21, C7) + 1) * F7 -> 300 | O7: =MAX(0, MIN(26, 999) - MAX(24, C7) + 1) * F7 -> 300 | P7: =SUM(G7:O7) -> 2600
A8: 5 | B8: Jira / Linear / project tooling | C8: 1 | D8: USD | E8: 60 | F8: =IFERROR(E8/INDEX(Assumptions!$C$10:$C$15,MATCH(D8,Assumptions!$A$10:$A$15,0)),0) -> 60 | G8: =MAX(0, MIN(2, 999) - MAX(1, C8) + 1) * F8 -> 120 | H8: =MAX(0, MIN(5, 999) - MAX(3, C8) + 1) * F8 -> 180 | I8: =MAX(0, MIN(8, 999) - MAX(6, C8) + 1) * F8 -> 180 | J8: =MAX(0, MIN(11, 999) - MAX(9, C8) + 1) * F8 -> 180 | K8: =MAX(0, MIN(14, 999) - MAX(12, C8) + 1) * F8 -> 180 | L8: =MAX(0, MIN(17, 999) - MAX(15, C8) + 1) * F8 -> 180 | M8: =MAX(0, MIN(20, 999) - MAX(18, C8) + 1) * F8 -> 180 | N8: =MAX(0, MIN(23, 999) - MAX(21, C8) + 1) * F8 -> 180 | O8: =MAX(0, MIN(26, 999) - MAX(24, C8) + 1) * F8 -> 180 | P8: =SUM(G8:O8) -> 1560
A9: 6 | B9: Monitoring & observability (Datadog) | C9: 3 | D9: USD | E9: 200 | F9: =IFERROR(E9/INDEX(Assumptions!$C$10:$C$15,MATCH(D9,Assumptions!$A$10:$A$15,0)),0) -> 200 | G9: =MAX(0, MIN(2, 999) - MAX(1, C9) + 1) * F9 -> 0 | H9: =MAX(0, MIN(5, 999) - MAX(3, C9) + 1) * F9 -> 600 | I9: =MAX(0, MIN(8, 999) - MAX(6, C9) + 1) * F9 -> 600 | J9: =MAX(0, MIN(11, 999) - MAX(9, C9) + 1) * F9 -> 600 | K9: =MAX(0, MIN(14, 999) - MAX(12, C9) + 1) * F9 -> 600 | L9: =MAX(0, MIN(17, 999) - MAX(15, C9) + 1) * F9 -> 600 | M9: =MAX(0, MIN(20, 999) - MAX(18, C9) + 1) * F9 -> 600 | N9: =MAX(0, MIN(23, 999) - MAX(21, C9) + 1) * F9 -> 600 | O9: =MAX(0, MIN(26, 999) - MAX(24, C9) + 1) * F9 -> 600 | P9: =SUM(G9:O9) -> 4800
A10: 7 | B10: Email, chat & productivity (MS365/GW) | C10: 1 | D10: USD | E10: 100 | F10: =IFERROR(E10/INDEX(Assumptions!$C$10:$C$15,MATCH(D10,Assumptions!$A$10:$A$15,0)),0) -> 100 | G10: =MAX(0, MIN(2, 999) - MAX(1, C10) + 1) * F10 -> 200 | H10: =MAX(0, MIN(5, 999) - MAX(3, C10) + 1) * F10 -> 300 | I10: =MAX(0, MIN(8, 999) - MAX(6, C10) + 1) * F10 -> 300 | J10: =MAX(0, MIN(11, 999) - MAX(9, C10) + 1) * F10 -> 300 | K10: =MAX(0, MIN(14, 999) - MAX(12, C10) + 1) * F10 -> 300 | L10: =MAX(0, MIN(17, 999) - MAX(15, C10) + 1) * F10 -> 300 | M10: =MAX(0, MIN(20, 999) - MAX(18, C10) + 1) * F10 -> 300 | N10: =MAX(0, MIN(23, 999) - MAX(21, C10) + 1) * F10 -> 300 | O10: =MAX(0, MIN(26, 999) - MAX(24, C10) + 1) * F10 -> 300 | P10: =SUM(G10:O10) -> 2600
A11: 8 | B11: Security tools (SSO, secrets) | C11: 1 | D11: USD | E11: 80 | F11: =IFERROR(E11/INDEX(Assumptions!$C$10:$C$15,MATCH(D11,Assumptions!$A$10:$A$15,0)),0) -> 80 | G11: =MAX(0, MIN(2, 999) - MAX(1, C11) + 1) * F11 -> 160 | H11: =MAX(0, MIN(5, 999) - MAX(3, C11) + 1) * F11 -> 240 | I11: =MAX(0, MIN(8, 999) - MAX(6, C11) + 1) * F11 -> 240 | J11: =MAX(0, MIN(11, 999) - MAX(9, C11) + 1) * F11 -> 240 | K11: =MAX(0, MIN(14, 999) - MAX(12, C11) + 1) * F11 -> 240 | L11: =MAX(0, MIN(17, 999) - MAX(15, C11) + 1) * F11 -> 240 | M11: =MAX(0, MIN(20, 999) - MAX(18, C11) + 1) * F11 -> 240 | N11: =MAX(0, MIN(23, 999) - MAX(21, C11) + 1) * F11 -> 240 | O11: =MAX(0, MIN(26, 999) - MAX(24, C11) + 1) * F11 -> 240 | P11: =SUM(G11:O11) -> 2080
A12: 9 | B12: CI/CD & testing services | C12: 3 | D12: USD | E12: 60 | F12: =IFERROR(E12/INDEX(Assumptions!$C$10:$C$15,MATCH(D12,Assumptions!$A$10:$A$15,0)),0) -> 60 | G12: =MAX(0, MIN(2, 999) - MAX(1, C12) + 1) * F12 -> 0 | H12: =MAX(0, MIN(5, 999) - MAX(3, C12) + 1) * F12 -> 180 | I12: =MAX(0, MIN(8, 999) - MAX(6, C12) + 1) * F12 -> 180 | J12: =MAX(0, MIN(11, 999) - MAX(9, C12) + 1) * F12 -> 180 | K12: =MAX(0, MIN(14, 999) - MAX(12, C12) + 1) * F12 -> 180 | L12: =MAX(0, MIN(17, 999) - MAX(15, C12) + 1) * F12 -> 180 | M12: =MAX(0, MIN(20, 999) - MAX(18, C12) + 1) * F12 -> 180 | N12: =MAX(0, MIN(23, 999) - MAX(21, C12) + 1) * F12 -> 180 | O12: =MAX(0, MIN(26, 999) - MAX(24, C12) + 1) * F12 -> 180 | P12: =SUM(G12:O12) -> 1440
B14: TOTAL SOFTWARE & INFRA (USD) | F14: =SUM(F4:F12) -> 1200 | G14: =SUM(G4:G12) -> 1880 | H14: =SUM(H4:H12) -> 3600 | I14: =SUM(I4:I12) -> 3600 | J14: =SUM(J4:J12) -> 3600 | K14: =SUM(K4:K12) -> 3600 | L14: =SUM(L4:L12) -> 3600 | M14: =SUM(M4:M12) -> 3600 | ... P14: =SUM(P4:P12) -> 30680

Sheet Hardware & Setup
A1: Hardware & One-off Setup (USD)
A3: # | B3: Item | C3: Purchase Month Idx | D3: Cur | E3: One-off Native | F3: One-off USD | G3: Q2 2026 | H3: Q3 2026 | I3: Q4 2026 | J3: Q1 2027 | K3: Q2 2027 | L3: Q3 2027 | M3: Q4 2027 | N3: Q1 2028 | O3: Q2 2028 | P3: Total USD
A4: 1 | B4: Laptops — core team (4) | C4: 1 | D4: USD | E4: 4800 | F4: =IFERROR(E4/INDEX(Assumptions!$C$10:$C$15,MATCH(D4,Assumptions!$A$10:$A$15,0)),0) -> 4800 | G4: =IF(AND(C4>=1, C4<=2), F4, 0) -> 4800 | H4: =IF(AND(C4>=3, C4<=5), F4, 0) -> 0 | I4: =IF(AND(C4>=6, C4<=8), F4, 0) -> 0 | J4: =IF(AND(C4>=9, C4<=11), F4, 0) -> 0 | K4: =IF(AND(C4>=12, C4<=14), F4, 0) -> 0 | L4: =IF(AND(C4>=15, C4<=17), F4, 0) -> 0 | M4: =IF(AND(C4>=18, C4<=20), F4, 0) -> 0 | N4: =IF(AND(C4>=21, C4<=23), F4, 0) -> 0 | O4: =IF(AND(C4>=24, C4<=26), F4, 0) -> 0 | P4: =SUM(G4:O4) -> 4800
A5: 2 | B5: Laptops — new hires (2 Senior) | C5: 3 | D5: USD | E5: 3000 | F5: =IFERROR(E5/INDEX(Assumptions!$C$10:$C$15,MATCH(D5,Assumptions!$A$10:$A$15,0)),0) -> 3000 | G5: =IF(AND(C5>=1, C5<=2), F5, 0) -> 0 | H5: =IF(AND(C5>=3, C5<=5), F5, 0) -> 3000 | I5: =IF(AND(C5>=6, C5<=8), F5, 0) -> 0 | J5: =IF(AND(C5>=9, C5<=11), F5, 0) -> 0 | K5: =IF(AND(C5>=12, C5<=14), F5, 0) -> 0 | L5: =IF(AND(C5>=15, C5<=17), F5, 0) -> 0 | M5: =IF(AND(C5>=18, C5<=20), F5, 0) -> 0 | N5: =IF(AND(C5>=21, C5<=23), F5, 0) -> 0 | O5: =IF(AND(C5>=24, C5<=26), F5, 0) -> 0 | P5: =SUM(G5:O5) -> 3000
A6: 3 | B6: Laptops — add'l hires (4) | C6: 6 | D6: USD | E6: 4800 | F6: =IFERROR(E6/INDEX(Assumptions!$C$10:$C$15,MATCH(D6,Assumptions!$A$10:$A$15,0)),0) -> 4800 | G6: =IF(AND(C6>=1, C6<=2), F6, 0) -> 0 | H6: =IF(AND(C6>=3, C6<=5), F6, 0) -> 0 | I6: =IF(AND(C6>=6, C6<=8), F6, 0) -> 4800 | J6: =IF(AND(C6>=9, C6<=11), F6, 0) -> 0 | K6: =IF(AND(C6>=12, C6<=14), F6, 0) -> 0 | L6: =IF(AND(C6>=15, C6<=17), F6, 0) -> 0 | M6: =IF(AND(C6>=18, C6<=20), F6, 0) -> 0 | N6: =IF(AND(C6>=21, C6<=23), F6, 0) -> 0 | O6: =IF(AND(C6>=24, C6<=26), F6, 0) -> 0 | P6: =SUM(G6:O6) -> 4800
A7: 4 | B7: Monitors & peripherals | C7: 1 | D7: USD | E7: 1500 | F7: =IFERROR(E7/INDEX(Assumptions!$C$10:$C$15,MATCH(D7,Assumptions!$A$10:$A$15,0)),0) -> 1500 | G7: =IF(AND(C7>=1, C7<=2), F7, 0) -> 1500 | H7: =IF(AND(C7>=3, C7<=5), F7, 0) -> 0 | I7: =IF(AND(C7>=6, C7<=8), F7, 0) -> 0 | J7: =IF(AND(C7>=9, C7<=11), F7, 0) -> 0 | K7: =IF(AND(C7>=12, C7<=14), F7, 0) -> 0 | L7: =IF(AND(C7>=15, C7<=17), F7, 0) -> 0 | M7: =IF(AND(C7>=18, C7<=20), F7, 0) -> 0 | N7: =IF(AND(C7>=21, C7<=23), F7, 0) -> 0 | O7: =IF(AND(C7>=24, C7<=26), F7, 0) -> 0 | P7: =SUM(G7:O7) -> 1500
A8: 5 | B8: Office / remote setup kit | C8: 1 | D8: USD | E8: 1000 | F8: =IFERROR(E8/INDEX(Assumptions!$C$10:$C$15,MATCH(D8,Assumptions!$A$10:$A$15,0)),0) -> 1000 | G8: =IF(AND(C8>=1, C8<=2), F8, 0) -> 1000 | H8: =IF(AND(C8>=3, C8<=5), F8, 0) -> 0 | I8: =IF(AND(C8>=6, C8<=8), F8, 0) -> 0 | J8: =IF(AND(C8>=9, C8<=11), F8, 0) -> 0 | K8: =IF(AND(C8>=12, C8<=14), F8, 0) -> 0 | L8: =IF(AND(C8>=15, C8<=17), F8, 0) -> 0 | M8: =IF(AND(C8>=18, C8<=20), F8, 0) -> 0 | N8: =IF(AND(C8>=21, C8<=23), F8, 0) -> 0 | O8: =IF(AND(C8>=24, C8<=26), F8, 0) -> 0 | P8: =SUM(G8:O8) -> 1000
A9: 6 | B9: Contingency — replacements/expansion | C9: 12 | D9: USD | E9: 1500 | F9: =IFERROR(E9/INDEX(Assumptions!$C$10:$C$15,MATCH(D9,Assumptions!$A$10:$A$15,0)),0) -> 1500 | G9: =IF(AND(C9>=1, C9<=2), F9, 0) -> 0 | H9: =IF(AND(C9>=3, C9<=5), F9, 0) -> 0 | I9: =IF(AND(C9>=6, C9<=8), F9, 0) -> 0 | J9: =IF(AND(C9>=9, C9<=11), F9, 0) -> 0 | K9: =IF(AND(C9>=12, C9<=14), F9, 0) -> 1500 | L9: =IF(AND(C9>=15, C9<=17), F9, 0) -> 0 | M9: =IF(AND(C9>=18, C9<=20), F9, 0) -> 0 | N9: =IF(AND(C9>=21, C9<=23), F9, 0) -> 0 | O9: =IF(AND(C9>=24, C9<=26), F9, 0) -> 0 | P9: =SUM(G9:O9) -> 1500
B11: TOTAL HARDWARE & SETUP (USD) | F11: =SUM(F4:F9) -> 16600 | G11: =SUM(G4:G9) -> 7300 | H11: =SUM(H4:H9) -> 3000 | I11: =SUM(I4:I9) -> 4800 | J11: =SUM(J4:J9) -> 0 | K11: =SUM(K4:K9) -> 1500 | L11: =SUM(L4:L9) -> 0 | M11: =SUM(M4:M9) -> 0 | ... P11: =SUM(P4:P9) -> 16600

Sheet Quarterly Summary
A1: Quarterly Summary — All Categories (USD)
A3: # | B3: Category | C3: Q2 2026 | D3: Q3 2026 | E3: Q4 2026 | F3: Q1 2027 | G3: Q2 2027 | H3: Q3 2027 | I3: Q4 2027 | J3: Q1 2028 | K3: Q2 2028 | L3: Total
A4: 1 | B4: Salaries & benefits | C4: ='Salary Schedule'!E17 -> 5040 | D4: ='Salary Schedule'!F17 -> 20880 | E4: ='Salary Schedule'!G17 -> 26856 | F4: ='Salary Schedule'!H17 -> 26856 | G4: ='Salary Schedule'!I17 -> 26856 | H4: ='Salary Schedule'!J17 -> 26856 | I4: ='Salary Schedule'!K17 -> 26856 | J4: ='Salary Schedule'!L17 -> 26856 | K4: ='Salary Schedule'!M17 -> 26856 | L4: =SUM(C4:K4) -> 213912
A5: 2 | B5: Contractors / vendors | C5: =Contractors!H9 -> 600 | D5: =Contractors!I9 -> 1900 | E5: =Contractors!J9 -> 300 | F5: =Contractors!K9 -> 2500 | G5: =Contractors!L9 -> 0 | H5: =Contractors!M9 -> 0 | I5: =Contractors!N9 -> 0 | J5: =Contractors!O9 -> 0 | K5: =Contractors!P9 -> 0 | L5: =SUM(C5:K5) -> 5300
A6: 3 | B6: Software & infra | C6: ='Software & Infra'!G14 -> 1880 | D6: ='Software & Infra'!H14 -> 3600 | E6: ='Software & Infra'!I14 -> 3600 | F6: ='Software & Infra'!J14 -> 3600 | G6: ='Software & Infra'!K14 -> 3600 | H6: ='Software & Infra'!L14 -> 3600 | I6: ='Software & Infra'!M14 -> 3600 | J6: ='Software & Infra'!N14 -> 3600 | K6: ='Software & Infra'!O14 -> 3600 | L6: =SUM(C6:K6) -> 30680
A7: 4 | B7: Hardware & setup | C7: ='Hardware & Setup'!G11 -> 7300 | D7: ='Hardware & Setup'!H11 -> 3000 | E7: ='Hardware & Setup'!I11 -> 4800 | F7: ='Hardware & Setup'!J11 -> 0 | G7: ='Hardware & Setup'!K11 -> 1500 | H7: ='Hardware & Setup'!L11 -> 0 | I7: ='Hardware & Setup'!M11 -> 0 | J7: ='Hardware & Setup'!N11 -> 0 | K7: ='Hardware & Setup'!O11 -> 0 | L7: =SUM(C7:K7) -> 16600
B9: GRAND TOTAL (USD) | C9: =SUM(C4:C7) -> 14820 | D9: =SUM(D4:D7) -> 29380 | E9: =SUM(E4:E7) -> 35556 | F9: =SUM(F4:F7) -> 32956 | G9: =SUM(G4:G7) -> 31956 | H9: =SUM(H4:H7) -> 30456 | I9: =SUM(I4:I7) -> 30456 | J9: =SUM(J4:J7) -> 30456 | ... L9: =SUM(L4:L7) -> 266492
B11: Cumulative (running USD total) | C11: =C9 -> 14820 | D11: =C11+D9 -> 44200 | E11: =D11+E9 -> 79756 | F11: =E11+F9 -> 112712 | G11: =F11+G9 -> 144668 | H11: =G11+H9 -> 175124 | I11: =H11+I9 -> 205580 | J11: =I11+J9 -> 236036 | K11: =J11+K9 -> 266492
A14: Native-currency view (total spend by native currency, across entire horizon)
B15: Currency | C15: Total Native | D15: Total USD | E15: Source
B16: EGP | C16: =D16*INDEX(Assumptions!$C$10:$C$15,MATCH(B16,Assumptions!$A$10:$A$15,0)) -> 10835600 | D16: =SUMPRODUCT(('Salary Schedule'!$C$4:$C$15="EGP")*'Salary Schedule'!$N$4:$N$15)+SUMPRODUCT((Contractors!$E$4:$E$7="EGP")*Contractors!$Q$4:$Q$7)+SUMPRODUCT(('Software & Infra'!$D$4:$D$12="EGP")*'Software & Infra'!$P$4:$P$12)+SUMPRODUCT(('Hardware & Setup'!$D$4:$D$9="EGP")*'Hardware & Setup'!$P$4:$P$9) -> 216712 | E16: All categories, full horizon
B17: USD | C17: =D17*INDEX(Assumptions!$C$10:$C$15,MATCH(B17,Assumptions!$A$10:$A$15,0)) -> 49780 | D17: =SUMPRODUCT(('Salary Schedule'!$C$4:$C$15="USD")*'Salary Schedule'!$N$4:$N$15)+SUMPRODUCT((Contractors!$E$4:$E$7="USD")*Contractors!$Q$4:$Q$7)+SUMPRODUCT(('Software & Infra'!$D$4:$D$12="USD")*'Software & Infra'!$P$4:$P$12)+SUMPRODUCT(('Hardware & Setup'!$D$4:$D$9="USD")*'Hardware & Setup'!$P$4:$P$9) -> 49780 | E17: All categories, full horizon
B19: USD check (all currencies) | D19: =SUM(D16:D17) -> 266492
